{
  "seed": 141,
  "grafo": {
    "directed": true,
    "multigraph": false,
    "graph": {},
    "nodes": [
      {
        "horror": 1382.1049773286354,
        "dim": 0,
        "timestamp": "2026-01-20T20:31:16.344758",
        "desc": "El abismo total",
        "label": "CERO ABSOLUTO",
        "position": [
          0,
          0,
          0
        ],
        "shape": "sphere",
        "geometry": "blackhole",
        "id": "CERO_ABSOLUTO"
      },
      {
        "horror": 1545.7725567324092,
        "dim": 1,
        "timestamp": "2026-01-20T20:31:16.344758",
        "desc": "Traición absoluta (socios, instituciones, familia)",
        "label": "D1: Traición absoluta (socios, instituciones, familia)",
        "position": [
          35.831836216989814,
          -731.1470688444251,
          -125.78209792352095
        ],
        "shape": "sphere",
        "geometry": "default",
        "id": "D1"
      },
      {
        "horror": 2214.56476616109,
        "dim": 1,
        "sub_level": 1,
        "timestamp": "2026-01-20T20:31:16.344758",
        "desc": "Traición absoluta (socios, instituciones, familia) agravado x1.71",
        "label": "D1.1",
        "position": [
          -67.83739785523309,
          -866.0228445403206,
          -66.90810437928849
        ],
        "shape": "dot",
        "geometry": "default",
        "id": "D1.1"
      },
      {
        "horror": 2169.5665132237764,
        "dim": 1,
        "sub_level": 2,
        "timestamp": "2026-01-20T20:31:16.344758",
        "desc": "Traición absoluta (socios, instituciones, familia) agravado x1.79",
        "label": "D1.2",
        "position": [
          -62.38307268011873,
          -874.0956466757973,
          -97.56152745326884
        ],
        "shape": "dot",
        "geometry": "default",
        "id": "D1.2"
      },
      {
        "horror": 2352.005412914841,
        "dim": 1,
        "sub_level": 3,
        "timestamp": "2026-01-20T20:31:16.344758",
        "desc": "Traición absoluta (socios, instituciones, familia) agravado x1.75",
        "label": "D1.3",
        "position": [
          -50.52874868766668,
          -737.6821584473169,
          -169.39482381810222
        ],
        "shape": "dot",
        "geometry": "default",
        "id": "D1.3"
      },
      {
        "horror": 2027.5180227559383,
        "dim": 1,
        "sub_level": 4,
        "timestamp": "2026-01-20T20:31:16.344758",
        "desc": "Traición absoluta (socios, instituciones, familia) agravado x1.66",
        "label": "D1.4",
        "position": [
          31.52799209632255,
          -679.7483818475475,
          -192.00227465948132
        ],
        "shape": "dot",
        "geometry": "default",
        "id": "D1.4"
      },
      {
        "horror": 1782.9506888641806,
        "dim": 1,
        "sub_level": 5,
        "timestamp": "2026-01-20T20:31:16.344758",
        "desc": "Traición absoluta (socios, instituciones, familia) agravado x1.37",
        "label": "D1.5",
        "position": [
          151.50242923624012,
          -854.1688455032652,
          -49.83354111620923
        ],
        "shape": "dot",
        "geometry": "default",
        "id": "D1.5"
      },
      {
        "horror": 2157.2175293967343,
        "dim": 1,
        "sub_level": 6,
        "timestamp": "2026-01-20T20:31:16.344758",
        "desc": "Traición absoluta (socios, instituciones, familia) agravado x1.73",
        "label": "D1.6",
        "position": [
          54.88762659286181,
          -825.5595955754238,
          -258.61487494014636
        ],
        "shape": "dot",
        "geometry": "default",
        "id": "D1.6"
      },
      {
        "horror": 2009.7485572613298,
        "dim": 1,
        "sub_level": 7,
        "timestamp": "2026-01-20T20:31:16.344758",
        "desc": "Traición absoluta (socios, instituciones, familia) agravado x1.68",
        "label": "D1.7",
        "position": [
          177.39926966515736,
          -675.8420689406554,
          14.090219306537676
        ],
        "shape": "dot",
        "geometry": "default",
        "id": "D1.7"
      },
      {
        "horror": 2347.1451749083776,
        "dim": 1,
        "sub_level": 8,
        "timestamp": "2026-01-20T20:31:16.344758",
        "desc": "Traición absoluta (socios, instituciones, familia) agravado x1.77",
        "label": "D1.8",
        "position": [
          -51.046986625580246,
          -839.485864720355,
          -172.5109455987878
        ],
        "shape": "dot",
        "geometry": "default",
        "id": "D1.8"
      },
      {
        "horror": 1273.5655331931464,
        "dim": 2,
        "timestamp": "2026-01-20T20:31:16.344758",
        "desc": "Colapso económico / pobreza perpetua / mendicidad",
        "label": "D2: Colapso económico / pobreza perpetua / mendicidad",
        "position": [
          -340.3707938174939,
          41.45390694052594,
          -222.5450574560839
        ],
        "shape": "sphere",
        "geometry": "default",
        "id": "D2"
      },
      {
        "horror": 2035.2278763982226,
        "dim": 2,
        "sub_level": 1,
        "timestamp": "2026-01-20T20:31:16.344758",
        "desc": "Colapso económico / pobreza perpetua / mendicidad agravado x1.84",
        "label": "D2.1",
        "position": [
          -205.10924283808805,
          -10.39640796182401,
          -222.32184977808967
        ],
        "shape": "dot",
        "geometry": "default",
        "id": "D2.1"
      },
      {
        "horror": 1693.5986665300113,
        "dim": 2,
        "sub_level": 2,
        "timestamp": "2026-01-20T20:31:16.344758",
        "desc": "Colapso económico / pobreza perpetua / mendicidad agravado x1.55",
        "label": "D2.2",
        "position": [
          -346.31491714867286,
          104.90646552827306,
          -186.8462293432291
        ],
        "shape": "dot",
        "geometry": "default",
        "id": "D2.2"
      },
      {
        "horror": 1717.5653614708408,
        "dim": 2,
        "sub_level": 3,
        "timestamp": "2026-01-20T20:31:16.344758",
        "desc": "Colapso económico / pobreza perpetua / mendicidad agravado x1.64",
        "label": "D2.3",
        "position": [
          -335.73672355568146,
          25.153737752433074,
          -248.96869544323272
        ],
        "shape": "dot",
        "geometry": "default",
        "id": "D2.3"
      },
      {
        "horror": 1727.9193443477864,
        "dim": 2,
        "sub_level": 4,
        "timestamp": "2026-01-20T20:31:16.344758",
        "desc": "Colapso económico / pobreza perpetua / mendicidad agravado x1.41",
        "label": "D2.4",
        "position": [
          -283.1617583882882,
          -54.75151232688438,
          -77.26292468446371
        ],
        "shape": "dot",
        "geometry": "default",
        "id": "D2.4"
      },
      {
        "horror": 1817.2902516606302,
        "dim": 2,
        "sub_level": 5,
        "timestamp": "2026-01-20T20:31:16.344758",
        "desc": "Colapso económico / pobreza perpetua / mendicidad agravado x1.76",
        "label": "D2.5",
        "position": [
          -356.6536095504433,
          164.03134708013886,
          -273.00381851785454
        ],
        "shape": "dot",
        "geometry": "default",
        "id": "D2.5"
      },
      {
        "horror": 1808.2162445388444,
        "dim": 2,
        "sub_level": 6,
        "timestamp": "2026-01-20T20:31:16.344758",
        "desc": "Colapso económico / pobreza perpetua / mendicidad agravado x1.50",
        "label": "D2.6",
        "position": [
          -361.5820450889365,
          76.2397491209878,
          -172.9405276959855
        ],
        "shape": "dot",
        "geometry": "default",
        "id": "D2.6"
      },
      {
        "horror": 1595.9949907410937,
        "dim": 2,
        "sub_level": 7,
        "timestamp": "2026-01-20T20:31:16.344758",
        "desc": "Colapso económico / pobreza perpetua / mendicidad agravado x1.51",
        "label": "D2.7",
        "position": [
          -192.39164841559318,
          154.5807823279157,
          -289.06282439384427
        ],
        "shape": "dot",
        "geometry": "default",
        "id": "D2.7"
      },
      {
        "horror": 1743.3117159492824,
        "dim": 2,
        "sub_level": 8,
        "timestamp": "2026-01-20T20:31:16.344758",
        "desc": "Colapso económico / pobreza perpetua / mendicidad agravado x1.50",
        "label": "D2.8",
        "position": [
          -394.07772343390155,
          134.63362770602495,
          -121.8123427358081
        ],
        "shape": "dot",
        "geometry": "default",
        "id": "D2.8"
      },
      {
        "horror": 1263.6576906475618,
        "dim": 3,
        "timestamp": "2026-01-20T20:31:16.344758",
        "desc": "Aislamiento total (nadie real, nakamas falsos)",
        "label": "D3: Aislamiento total (nadie real, nakamas falsos)",
        "position": [
          -312.28617918341774,
          -791.9679313812165,
          -652.1134949256368
        ],
        "shape": "sphere",
        "geometry": "default",
        "id": "D3"
      },
      {
        "horror": 1678.3503546935226,
        "dim": 3,
        "sub_level": 1,
        "timestamp": "2026-01-20T20:31:16.344758",
        "desc": "Aislamiento total (nadie real, nakamas falsos) agravado x1.47",
        "label": "D3.1",
        "position": [
          -459.9490526249655,
          -929.1134361218596,
          -633.4390999537175
        ],
        "shape": "dot",
        "geometry": "default",
        "id": "D3.1"
      },
      {
        "horror": 1865.055360058599,
        "dim": 3,
        "sub_level": 2,
        "timestamp": "2026-01-20T20:31:16.344758",
        "desc": "Aislamiento total (nadie real, nakamas falsos) agravado x1.78",
        "label": "D3.2",
        "position": [
          -418.33107971681363,
          -830.7366613975813,
          -777.127501617799
        ],
        "shape": "dot",
        "geometry": "default",
        "id": "D3.2"
      },
      {
        "horror": 1924.1581586615948,
        "dim": 3,
        "sub_level": 3,
        "timestamp": "2026-01-20T20:31:16.344758",
        "desc": "Aislamiento total (nadie real, nakamas falsos) agravado x1.60",
        "label": "D3.3",
        "position": [
          -254.06839613873362,
          -756.4560521277673,
          -659.984058254037
        ],
        "shape": "dot",
        "geometry": "default",
        "id": "D3.3"
      },
      {
        "horror": 1561.255020656352,
        "dim": 3,
        "sub_level": 4,
        "timestamp": "2026-01-20T20:31:16.344758",
        "desc": "Aislamiento total (nadie real, nakamas falsos) agravado x1.41",
        "label": "D3.4",
        "position": [
          -395.4190284305595,
          -832.9454359444902,
          -781.2978761498633
        ],
        "shape": "dot",
        "geometry": "default",
        "id": "D3.4"
      },
      {
        "horror": 1740.6020490842513,
        "dim": 3,
        "sub_level": 5,
        "timestamp": "2026-01-20T20:31:16.344758",
        "desc": "Aislamiento total (nadie real, nakamas falsos) agravado x1.40",
        "label": "D3.5",
        "position": [
          -195.93107196065006,
          -741.6289209458749,
          -612.58208959882
        ],
        "shape": "dot",
        "geometry": "default",
        "id": "D3.5"
      },
      {
        "horror": 1698.640111479852,
        "dim": 3,
        "sub_level": 6,
        "timestamp": "2026-01-20T20:31:16.344758",
        "desc": "Aislamiento total (nadie real, nakamas falsos) agravado x1.64",
        "label": "D3.6",
        "position": [
          -222.21626298527997,
          -917.0723476110238,
          -526.5985289029131
        ],
        "shape": "dot",
        "geometry": "default",
        "id": "D3.6"
      },
      {
        "horror": 1654.721887092978,
        "dim": 3,
        "sub_level": 7,
        "timestamp": "2026-01-20T20:31:16.344758",
        "desc": "Aislamiento total (nadie real, nakamas falsos) agravado x1.44",
        "label": "D3.7",
        "position": [
          -192.3086439196719,
          -780.269121544839,
          -678.3287287526832
        ],
        "shape": "dot",
        "geometry": "default",
        "id": "D3.7"
      },
      {
        "horror": 1899.9745311159654,
        "dim": 3,
        "sub_level": 8,
        "timestamp": "2026-01-20T20:31:16.344758",
        "desc": "Aislamiento total (nadie real, nakamas falsos) agravado x1.51",
        "label": "D3.8",
        "position": [
          -211.05845135247657,
          -914.0655483652365,
          -555.0314008198968
        ],
        "shape": "dot",
        "geometry": "default",
        "id": "D3.8"
      },
      {
        "horror": 1175.304071734284,
        "dim": 4,
        "timestamp": "2026-01-20T20:31:16.344758",
        "desc": "Muerte cercana o pérdida irreparable (hijo, libertad)",
        "label": "D4: Muerte cercana o pérdida irreparable (hijo, libertad)",
        "position": [
          -539.224966022108,
          -461.56695320825065,
          -528.6157925374773
        ],
        "shape": "sphere",
        "geometry": "default",
        "id": "D4"
      },
      {
        "horror": 1682.0060591865815,
        "dim": 4,
        "sub_level": 1,
        "timestamp": "2026-01-20T20:31:16.344758",
        "desc": "Muerte cercana o pérdida irreparable (hijo, libertad) agravado x1.60",
        "label": "D4.1",
        "position": [
          -537.6631512824015,
          -567.9058929606705,
          -599.5407145857976
        ],
        "shape": "dot",
        "geometry": "default",
        "id": "D4.1"
      },
      {
        "horror": 1506.5214428803642,
        "dim": 4,
        "sub_level": 2,
        "timestamp": "2026-01-20T20:31:16.344758",
        "desc": "Muerte cercana o pérdida irreparable (hijo, libertad) agravado x1.73",
        "label": "D4.2",
        "position": [
          -491.9667275967099,
          -396.9533553165421,
          -677.048561461651
        ],
        "shape": "dot",
        "geometry": "default",
        "id": "D4.2"
      },
      {
        "horror": 1547.2039054875836,
        "dim": 4,
        "sub_level": 3,
        "timestamp": "2026-01-20T20:31:16.344758",
        "desc": "Muerte cercana o pérdida irreparable (hijo, libertad) agravado x1.83",
        "label": "D4.3",
        "position": [
          -571.671629522316,
          -311.7986122906497,
          -429.6597276643106
        ],
        "shape": "dot",
        "geometry": "default",
        "id": "D4.3"
      },
      {
        "horror": 1633.320905115722,
        "dim": 4,
        "sub_level": 4,
        "timestamp": "2026-01-20T20:31:16.344758",
        "desc": "Muerte cercana o pérdida irreparable (hijo, libertad) agravado x1.74",
        "label": "D4.4",
        "position": [
          -442.44749260893195,
          -490.93950778512084,
          -480.8450631447863
        ],
        "shape": "dot",
        "geometry": "default",
        "id": "D4.4"
      },
      {
        "horror": 1742.702070635562,
        "dim": 4,
        "sub_level": 5,
        "timestamp": "2026-01-20T20:31:16.344758",
        "desc": "Muerte cercana o pérdida irreparable (hijo, libertad) agravado x1.78",
        "label": "D4.5",
        "position": [
          -440.43732652238964,
          -474.6625484495932,
          -595.5461248986373
        ],
        "shape": "dot",
        "geometry": "default",
        "id": "D4.5"
      },
      {
        "horror": 1890.9862878003569,
        "dim": 4,
        "sub_level": 6,
        "timestamp": "2026-01-20T20:31:16.344758",
        "desc": "Muerte cercana o pérdida irreparable (hijo, libertad) agravado x1.83",
        "label": "D4.6",
        "position": [
          -639.5643473465359,
          -344.22426119506997,
          -620.0048174789819
        ],
        "shape": "dot",
        "geometry": "default",
        "id": "D4.6"
      },
      {
        "horror": 1643.795199855196,
        "dim": 4,
        "sub_level": 7,
        "timestamp": "2026-01-20T20:31:16.344758",
        "desc": "Muerte cercana o pérdida irreparable (hijo, libertad) agravado x1.52",
        "label": "D4.7",
        "position": [
          -469.32204653725,
          -502.4428538139936,
          -598.9514124143856
        ],
        "shape": "dot",
        "geometry": "default",
        "id": "D4.7"
      },
      {
        "horror": 1427.4117712316652,
        "dim": 4,
        "sub_level": 8,
        "timestamp": "2026-01-20T20:31:16.344758",
        "desc": "Muerte cercana o pérdida irreparable (hijo, libertad) agravado x1.66",
        "label": "D4.8",
        "position": [
          -482.8288151862871,
          -517.5713571185026,
          -591.1065680400382
        ],
        "shape": "dot",
        "geometry": "default",
        "id": "D4.8"
      },
      {
        "horror": 1516.8827010234643,
        "dim": 5,
        "timestamp": "2026-01-20T20:31:16.344758",
        "desc": "Colapso cognitivo irreversible (fármacos, internación)",
        "label": "D5: Colapso cognitivo irreversible (fármacos, internación)",
        "position": [
          127.38658159300212,
          705.6318359374527,
          -654.0567468924689
        ],
        "shape": "sphere",
        "geometry": "default",
        "id": "D5"
      },
      {
        "horror": 1986.7041994044819,
        "dim": 5,
        "sub_level": 1,
        "timestamp": "2026-01-20T20:31:16.344758",
        "desc": "Colapso cognitivo irreversible (fármacos, internación) agravado x1.56",
        "label": "D5.1",
        "position": [
          180.25503780289347,
          763.1278772852322,
          -550.7453808675438
        ],
        "shape": "dot",
        "geometry": "default",
        "id": "D5.1"
      },
      {
        "horror": 1939.5273723914204,
        "dim": 5,
        "sub_level": 2,
        "timestamp": "2026-01-20T20:31:16.344758",
        "desc": "Colapso cognitivo irreversible (fármacos, internación) agravado x1.46",
        "label": "D5.2",
        "position": [
          25.385766417885094,
          659.6553609412065,
          -545.2929300125095
        ],
        "shape": "dot",
        "geometry": "default",
        "id": "D5.2"
      },
      {
        "horror": 1871.0940014183448,
        "dim": 5,
        "sub_level": 3,
        "timestamp": "2026-01-20T20:31:16.344758",
        "desc": "Colapso cognitivo irreversible (fármacos, internación) agravado x1.37",
        "label": "D5.3",
        "position": [
          35.34773085410855,
          572.826879440303,
          -518.9867307356341
        ],
        "shape": "dot",
        "geometry": "default",
        "id": "D5.3"
      },
      {
        "horror": 2036.754849717585,
        "dim": 5,
        "sub_level": 4,
        "timestamp": "2026-01-20T20:31:16.344758",
        "desc": "Colapso cognitivo irreversible (fármacos, internación) agravado x1.54",
        "label": "D5.4",
        "position": [
          -18.671512772408022,
          853.8380916495607,
          -605.037570655215
        ],
        "shape": "dot",
        "geometry": "default",
        "id": "D5.4"
      },
      {
        "horror": 2128.6476807387526,
        "dim": 5,
        "sub_level": 5,
        "timestamp": "2026-01-20T20:31:16.344758",
        "desc": "Colapso cognitivo irreversible (fármacos, internación) agravado x1.72",
        "label": "D5.5",
        "position": [
          205.3600382938385,
          829.2738009942921,
          -519.1018504599339
        ],
        "shape": "dot",
        "geometry": "default",
        "id": "D5.5"
      },
      {
        "horror": 2074.301792933256,
        "dim": 5,
        "sub_level": 6,
        "timestamp": "2026-01-20T20:31:16.344758",
        "desc": "Colapso cognitivo irreversible (fármacos, internación) agravado x1.65",
        "label": "D5.6",
        "position": [
          75.88915946919504,
          619.3273176898201,
          -607.7937592695434
        ],
        "shape": "dot",
        "geometry": "default",
        "id": "D5.6"
      },
      {
        "horror": 2351.428456326301,
        "dim": 5,
        "sub_level": 7,
        "timestamp": "2026-01-20T20:31:16.344758",
        "desc": "Colapso cognitivo irreversible (fármacos, internación) agravado x1.68",
        "label": "D5.7",
        "position": [
          227.26629502432118,
          631.7677859446123,
          -630.2159796545694
        ],
        "shape": "dot",
        "geometry": "default",
        "id": "D5.7"
      },
      {
        "horror": 2358.1964448981266,
        "dim": 5,
        "sub_level": 8,
        "timestamp": "2026-01-20T20:31:16.344758",
        "desc": "Colapso cognitivo irreversible (fármacos, internación) agravado x1.75",
        "label": "D5.8",
        "position": [
          256.04169311058126,
          583.3372556933653,
          -766.7336252691427
        ],
        "shape": "dot",
        "geometry": "default",
        "id": "D5.8"
      },
      {
        "horror": 1504.317125577299,
        "dim": 6,
        "timestamp": "2026-01-20T20:31:16.344758",
        "desc": "Vacío existencial / pérdida propósito (33 años tristeza)",
        "label": "D6: Vacío existencial / pérdida propósito (33 años tristeza)",
        "position": [
          603.6857457635153,
          145.86355356746844,
          -449.5770006467435
        ],
        "shape": "sphere",
        "geometry": "default",
        "id": "D6"
      },
      {
        "horror": 2172.0417724129825,
        "dim": 6,
        "sub_level": 1,
        "timestamp": "2026-01-20T20:31:16.344758",
        "desc": "Vacío existencial / pérdida propósito (33 años tristeza) agravado x1.58",
        "label": "D6.1",
        "position": [
          713.257947004905,
          15.868973460983142,
          -348.1385602419033
        ],
        "shape": "dot",
        "geometry": "default",
        "id": "D6.1"
      },
      {
        "horror": 1735.2736944307976,
        "dim": 6,
        "sub_level": 2,
        "timestamp": "2026-01-20T20:31:16.344758",
        "desc": "Vacío existencial / pérdida propósito (33 años tristeza) agravado x1.38",
        "label": "D6.2",
        "position": [
          728.5946918298357,
          19.50047916148091,
          -482.950471029519
        ],
        "shape": "dot",
        "geometry": "default",
        "id": "D6.2"
      },
      {
        "horror": 2245.609816739903,
        "dim": 6,
        "sub_level": 3,
        "timestamp": "2026-01-20T20:31:16.344758",
        "desc": "Vacío existencial / pérdida propósito (33 años tristeza) agravado x1.78",
        "label": "D6.3",
        "position": [
          708.4156971121084,
          213.53983523648003,
          -562.7362114628412
        ],
        "shape": "dot",
        "geometry": "default",
        "id": "D6.3"
      },
      {
        "horror": 2314.787429562134,
        "dim": 6,
        "sub_level": 4,
        "timestamp": "2026-01-20T20:31:16.344758",
        "desc": "Vacío existencial / pérdida propósito (33 años tristeza) agravado x1.81",
        "label": "D6.4",
        "position": [
          598.6016503099262,
          54.042684496057035,
          -350.6220183009225
        ],
        "shape": "dot",
        "geometry": "default",
        "id": "D6.4"
      },
      {
        "horror": 1772.2473258753757,
        "dim": 6,
        "sub_level": 5,
        "timestamp": "2026-01-20T20:31:16.344758",
        "desc": "Vacío existencial / pérdida propósito (33 años tristeza) agravado x1.49",
        "label": "D6.5",
        "position": [
          635.6928186041177,
          72.31426540299564,
          -519.6584110719031
        ],
        "shape": "dot",
        "geometry": "default",
        "id": "D6.5"
      },
      {
        "horror": 1815.1585811320354,
        "dim": 6,
        "sub_level": 6,
        "timestamp": "2026-01-20T20:31:16.344758",
        "desc": "Vacío existencial / pérdida propósito (33 años tristeza) agravado x1.53",
        "label": "D6.6",
        "position": [
          606.521941870593,
          42.80669375519712,
          -459.16576859716486
        ],
        "shape": "dot",
        "geometry": "default",
        "id": "D6.6"
      },
      {
        "horror": 2070.4893012781145,
        "dim": 6,
        "sub_level": 7,
        "timestamp": "2026-01-20T20:31:16.344758",
        "desc": "Vacío existencial / pérdida propósito (33 años tristeza) agravado x1.57",
        "label": "D6.7",
        "position": [
          712.8751541648165,
          128.03669298059341,
          -307.28542577124904
        ],
        "shape": "dot",
        "geometry": "default",
        "id": "D6.7"
      },
      {
        "horror": 1776.432839824983,
        "dim": 6,
        "sub_level": 8,
        "timestamp": "2026-01-20T20:31:16.344758",
        "desc": "Vacío existencial / pérdida propósito (33 años tristeza) agravado x1.41",
        "label": "D6.8",
        "position": [
          598.8238102743271,
          242.4294607769182,
          -505.68520109416795
        ],
        "shape": "dot",
        "geometry": "default",
        "id": "D6.8"
      },
      {
        "horror": 1146.9247986823023,
        "dim": 7,
        "timestamp": "2026-01-20T20:31:16.344758",
        "desc": "Humillación pública perpetua (desprecio, rechazo ancestral)",
        "label": "D7: Humillación pública perpetua (desprecio, rechazo ancestral)",
        "position": [
          485.2003157476129,
          -683.3956471572794,
          315.9569587695694
        ],
        "shape": "sphere",
        "geometry": "default",
        "id": "D7"
      },
      {
        "horror": 1643.1239081345536,
        "dim": 7,
        "sub_level": 1,
        "timestamp": "2026-01-20T20:31:16.344758",
        "desc": "Humillación pública perpetua (desprecio, rechazo ancestral) agravado x1.84",
        "label": "D7.1",
        "position": [
          483.2639331604257,
          -539.7348379644985,
          214.57099418742953
        ],
        "shape": "dot",
        "geometry": "default",
        "id": "D7.1"
      },
      {
        "horror": 1539.063760838133,
        "dim": 7,
        "sub_level": 2,
        "timestamp": "2026-01-20T20:31:16.344758",
        "desc": "Humillación pública perpetua (desprecio, rechazo ancestral) agravado x1.75",
        "label": "D7.2",
        "position": [
          579.0264095386915,
          -699.3834916165433,
          233.690506894414
        ],
        "shape": "dot",
        "geometry": "default",
        "id": "D7.2"
      },
      {
        "horror": 1557.4486011499598,
        "dim": 7,
        "sub_level": 3,
        "timestamp": "2026-01-20T20:31:16.344758",
        "desc": "Humillación pública perpetua (desprecio, rechazo ancestral) agravado x1.42",
        "label": "D7.3",
        "position": [
          613.7386635790227,
          -791.6790892798048,
          274.41007002817594
        ],
        "shape": "dot",
        "geometry": "default",
        "id": "D7.3"
      },
      {
        "horror": 1615.7404797009435,
        "dim": 7,
        "sub_level": 4,
        "timestamp": "2026-01-20T20:31:16.344758",
        "desc": "Humillación pública perpetua (desprecio, rechazo ancestral) agravado x1.71",
        "label": "D7.4",
        "position": [
          499.08266426202186,
          -709.7824608298707,
          404.2041824585984
        ],
        "shape": "dot",
        "geometry": "default",
        "id": "D7.4"
      },
      {
        "horror": 1773.8952340166152,
        "dim": 7,
        "sub_level": 5,
        "timestamp": "2026-01-20T20:31:16.344758",
        "desc": "Humillación pública perpetua (desprecio, rechazo ancestral) agravado x1.72",
        "label": "D7.5",
        "position": [
          490.689885636344,
          -737.9753025599681,
          387.53818029063933
        ],
        "shape": "dot",
        "geometry": "default",
        "id": "D7.5"
      },
      {
        "horror": 1509.2019794699565,
        "dim": 7,
        "sub_level": 6,
        "timestamp": "2026-01-20T20:31:16.344758",
        "desc": "Humillación pública perpetua (desprecio, rechazo ancestral) agravado x1.46",
        "label": "D7.6",
        "position": [
          354.0451729403537,
          -807.8444779156857,
          385.4622280651868
        ],
        "shape": "dot",
        "geometry": "default",
        "id": "D7.6"
      },
      {
        "horror": 1468.5921628362182,
        "dim": 7,
        "sub_level": 7,
        "timestamp": "2026-01-20T20:31:16.344758",
        "desc": "Humillación pública perpetua (desprecio, rechazo ancestral) agravado x1.45",
        "label": "D7.7",
        "position": [
          468.9915209402162,
          -791.4812302249246,
          368.8288451439491
        ],
        "shape": "dot",
        "geometry": "default",
        "id": "D7.7"
      },
      {
        "horror": 1251.1373034672372,
        "dim": 7,
        "sub_level": 8,
        "timestamp": "2026-01-20T20:31:16.344758",
        "desc": "Humillación pública perpetua (desprecio, rechazo ancestral) agravado x1.36",
        "label": "D7.8",
        "position": [
          413.9080093844908,
          -675.4790140853738,
          333.42375812847877
        ],
        "shape": "dot",
        "geometry": "default",
        "id": "D7.8"
      },
      {
        "horror": 1539.7548585461573,
        "dim": 8,
        "timestamp": "2026-01-20T20:31:16.344758",
        "desc": "Dolor crónico / enfermedad inducida (iatrogenia sistema)",
        "label": "D8: Dolor crónico / enfermedad inducida (iatrogenia sistema)",
        "position": [
          472.90071382393717,
          -379.60243787438816,
          -445.4602465608586
        ],
        "shape": "sphere",
        "geometry": "default",
        "id": "D8"
      },
      {
        "horror": 2122.898386894217,
        "dim": 8,
        "sub_level": 1,
        "timestamp": "2026-01-20T20:31:16.344758",
        "desc": "Dolor crónico / enfermedad inducida (iatrogenia sistema) agravado x1.74",
        "label": "D8.1",
        "position": [
          352.6158737685512,
          -455.9899211595188,
          -348.1917463076657
        ],
        "shape": "dot",
        "geometry": "default",
        "id": "D8.1"
      },
      {
        "horror": 1878.3314652469578,
        "dim": 8,
        "sub_level": 2,
        "timestamp": "2026-01-20T20:31:16.344758",
        "desc": "Dolor crónico / enfermedad inducida (iatrogenia sistema) agravado x1.42",
        "label": "D8.2",
        "position": [
          364.0148557043652,
          -348.34814456844623,
          -301.7093927278375
        ],
        "shape": "dot",
        "geometry": "default",
        "id": "D8.2"
      },
      {
        "horror": 2128.236229888277,
        "dim": 8,
        "sub_level": 3,
        "timestamp": "2026-01-20T20:31:16.344758",
        "desc": "Dolor crónico / enfermedad inducida (iatrogenia sistema) agravado x1.83",
        "label": "D8.3",
        "position": [
          368.3709174715865,
          -428.1422711606125,
          -472.5082046466656
        ],
        "shape": "dot",
        "geometry": "default",
        "id": "D8.3"
      },
      {
        "horror": 1710.45700184905,
        "dim": 8,
        "sub_level": 4,
        "timestamp": "2026-01-20T20:31:16.344758",
        "desc": "Dolor crónico / enfermedad inducida (iatrogenia sistema) agravado x1.37",
        "label": "D8.4",
        "position": [
          346.3163647563167,
          -502.3442475546487,
          -577.8367750702478
        ],
        "shape": "dot",
        "geometry": "default",
        "id": "D8.4"
      },
      {
        "horror": 2355.4161380254145,
        "dim": 8,
        "sub_level": 5,
        "timestamp": "2026-01-20T20:31:16.344758",
        "desc": "Dolor crónico / enfermedad inducida (iatrogenia sistema) agravado x1.82",
        "label": "D8.5",
        "position": [
          385.55277272382403,
          -448.5096690964405,
          -322.7792101551246
        ],
        "shape": "dot",
        "geometry": "default",
        "id": "D8.5"
      },
      {
        "horror": 2016.881467299301,
        "dim": 8,
        "sub_level": 6,
        "timestamp": "2026-01-20T20:31:16.344758",
        "desc": "Dolor crónico / enfermedad inducida (iatrogenia sistema) agravado x1.58",
        "label": "D8.6",
        "position": [
          438.57505671199823,
          -260.80377147863726,
          -298.10677891493714
        ],
        "shape": "dot",
        "geometry": "default",
        "id": "D8.6"
      },
      {
        "horror": 2217.403858745956,
        "dim": 8,
        "sub_level": 7,
        "timestamp": "2026-01-20T20:31:16.344758",
        "desc": "Dolor crónico / enfermedad inducida (iatrogenia sistema) agravado x1.69",
        "label": "D8.7",
        "position": [
          466.32399106094704,
          -387.2141131913728,
          -404.8234036882577
        ],
        "shape": "dot",
        "geometry": "default",
        "id": "D8.7"
      },
      {
        "horror": 2213.5407605293244,
        "dim": 8,
        "sub_level": 8,
        "timestamp": "2026-01-20T20:31:16.344758",
        "desc": "Dolor crónico / enfermedad inducida (iatrogenia sistema) agravado x1.73",
        "label": "D8.8",
        "position": [
          498.5303371889901,
          -325.933347644261,
          -525.259739365834
        ],
        "shape": "dot",
        "geometry": "default",
        "id": "D8.8"
      },
      {
        "horror": 1472.866292796541,
        "dim": 9,
        "timestamp": "2026-01-20T20:31:16.344758",
        "desc": "Autodestrucción inevitable (sistema gana, tú pierdes)",
        "label": "D9: Autodestrucción inevitable (sistema gana, tú pierdes)",
        "position": [
          500.4398671956426,
          -358.6857461358182,
          -255.16392511657125
        ],
        "shape": "sphere",
        "geometry": "default",
        "id": "D9"
      },
      {
        "horror": 1824.059223930681,
        "dim": 9,
        "sub_level": 1,
        "timestamp": "2026-01-20T20:31:16.344758",
        "desc": "Autodestrucción inevitable (sistema gana, tú pierdes) agravado x1.40",
        "label": "D9.1",
        "position": [
          464.85900169032624,
          -386.9192397095949,
          -187.47716147627764
        ],
        "shape": "dot",
        "geometry": "default",
        "id": "D9.1"
      },
      {
        "horror": 2034.63324106858,
        "dim": 9,
        "sub_level": 2,
        "timestamp": "2026-01-20T20:31:16.344758",
        "desc": "Autodestrucción inevitable (sistema gana, tú pierdes) agravado x1.58",
        "label": "D9.2",
        "position": [
          511.0973470767495,
          -475.7338189510267,
          -194.49702175691505
        ],
        "shape": "dot",
        "geometry": "default",
        "id": "D9.2"
      },
      {
        "horror": 1906.9386015935645,
        "dim": 9,
        "sub_level": 3,
        "timestamp": "2026-01-20T20:31:16.344758",
        "desc": "Autodestrucción inevitable (sistema gana, tú pierdes) agravado x1.52",
        "label": "D9.3",
        "position": [
          523.1161774170596,
          -430.89259790026756,
          -269.91180612311143
        ],
        "shape": "dot",
        "geometry": "default",
        "id": "D9.3"
      },
      {
        "horror": 2094.4890701186996,
        "dim": 9,
        "sub_level": 4,
        "timestamp": "2026-01-20T20:31:16.344758",
        "desc": "Autodestrucción inevitable (sistema gana, tú pierdes) agravado x1.66",
        "label": "D9.4",
        "position": [
          631.9244815505442,
          -346.28682964337077,
          -181.19552070148316
        ],
        "shape": "dot",
        "geometry": "default",
        "id": "D9.4"
      },
      {
        "horror": 2139.4165532045186,
        "dim": 9,
        "sub_level": 5,
        "timestamp": "2026-01-20T20:31:16.344758",
        "desc": "Autodestrucción inevitable (sistema gana, tú pierdes) agravado x1.68",
        "label": "D9.5",
        "position": [
          588.2063540682075,
          -463.3692261461312,
          -183.94476768323577
        ],
        "shape": "dot",
        "geometry": "default",
        "id": "D9.5"
      },
      {
        "horror": 2189.5243254710736,
        "dim": 9,
        "sub_level": 6,
        "timestamp": "2026-01-20T20:31:16.344758",
        "desc": "Autodestrucción inevitable (sistema gana, tú pierdes) agravado x1.78",
        "label": "D9.6",
        "position": [
          440.5516440423918,
          -451.77567603339685,
          -184.6172743806823
        ],
        "shape": "dot",
        "geometry": "default",
        "id": "D9.6"
      },
      {
        "horror": 1811.880125881804,
        "dim": 9,
        "sub_level": 7,
        "timestamp": "2026-01-20T20:31:16.344758",
        "desc": "Autodestrucción inevitable (sistema gana, tú pierdes) agravado x1.45",
        "label": "D9.7",
        "position": [
          549.0685676328693,
          -218.26492206267773,
          -210.2387889928992
        ],
        "shape": "dot",
        "geometry": "default",
        "id": "D9.7"
      },
      {
        "horror": 2127.309773122702,
        "dim": 9,
        "sub_level": 8,
        "timestamp": "2026-01-20T20:31:16.344758",
        "desc": "Autodestrucción inevitable (sistema gana, tú pierdes) agravado x1.62",
        "label": "D9.8",
        "position": [
          384.8063583904153,
          -363.1993405022928,
          -174.26027051744796
        ],
        "shape": "dot",
        "geometry": "default",
        "id": "D9.8"
      },
      {
        "horror": 2766.920026329164,
        "dim": "HYBRID",
        "desc": "Traición devora Muerte existencial",
        "label": "Traición devora Muerte existencial",
        "position": [
          -259.92539761245837,
          -620.0625061306553,
          -384.1731181162439
        ],
        "geometry": "default",
        "id": "HYBRID_D1.3_D4.7"
      },
      {
        "horror": 2769.209288853247,
        "dim": "HYBRID",
        "desc": "Colapso asfixia Vacío absoluto",
        "label": "Colapso asfixia Vacío absoluto",
        "position": [
          215.04809430830838,
          -19.44126943295062,
          -212.7007424631835
        ],
        "geometry": "default",
        "id": "HYBRID_D2.4_D6.1"
      },
      {
        "horror": 3208.5439142799264,
        "dim": "HYBRID",
        "desc": "Aislamiento asfixia Traición eterno",
        "label": "Aislamiento asfixia Traición eterno",
        "position": [
          -139.44792460385483,
          -890.0441964527786,
          -310.96975259959265
        ],
        "geometry": "default",
        "id": "HYBRID_D3.8_D1.1"
      },
      {
        "horror": 3356.7867004211794,
        "dim": "HYBRID",
        "desc": "Muerte perpetúa Autodestrucción terminal",
        "label": "Muerte perpetúa Autodestrucción terminal",
        "position": [
          -127.37899447806029,
          -353.7118008486814,
          -397.13254399821494
        ],
        "geometry": "default",
        "id": "HYBRID_D4.6_D9.8"
      },
      {
        "horror": 2614.891886536975,
        "dim": "HYBRID",
        "desc": "Colapso destruye Aislamiento ancestral",
        "label": "Colapso destruye Aislamiento ancestral",
        "position": [
          -80.29167055327076,
          -84.401020752786,
          -565.784410167227
        ],
        "geometry": "default",
        "id": "HYBRID_D5.3_D3.5"
      },
      {
        "horror": 3388.81425063938,
        "dim": "HYBRID",
        "desc": "Colapso amplifica Dolor eterno",
        "label": "Colapso amplifica Dolor eterno",
        "position": [
          346.7951430426341,
          122.27683637661977,
          -517.5196916714135
        ],
        "geometry": "default",
        "id": "HYBRID_D5.7_D8.7"
      },
      {
        "horror": 3181.6552161427153,
        "dim": "HYBRID",
        "desc": "Vacío traiciona Humillación eterno",
        "label": "Vacío traiciona Humillación eterno",
        "position": [
          601.9739163206245,
          -361.05316454949246,
          19.69981002436802
        ],
        "geometry": "default",
        "id": "HYBRID_D6.1_D7.5"
      },
      {
        "horror": 2802.6951253691086,
        "dim": "HYBRID",
        "desc": "Vacío destruye Humillación eterno",
        "label": "Vacío destruye Humillación eterno",
        "position": [
          663.3069088719196,
          -331.82119814960566,
          -16.43767787153655
        ],
        "geometry": "default",
        "id": "HYBRID_D6.7_D7.3"
      },
      {
        "horror": 2427.675858240503,
        "dim": "HYBRID",
        "desc": "Humillación traiciona Colapso cognitivo",
        "label": "Humillación traiciona Colapso cognitivo",
        "position": [
          247.18864367905064,
          -65.91293464185907,
          -88.2320424342802
        ],
        "geometry": "default",
        "id": "HYBRID_D7.7_D5.2"
      },
      {
        "horror": 2843.1187552756555,
        "dim": "HYBRID",
        "desc": "Dolor desgarra Colapso eterno",
        "label": "Dolor desgarra Colapso eterno",
        "position": [
          11.985363817443755,
          -186.13495998772635,
          -247.85986892555505
        ],
        "geometry": "default",
        "id": "HYBRID_D8.5_D2.6"
      },
      {
        "horror": 3162.6534210495374,
        "dim": "HYBRID",
        "desc": "Dolor traiciona Aislamiento terminal",
        "label": "Dolor traiciona Aislamiento terminal",
        "position": [
          92.2533302866323,
          -508.6299118032023,
          -479.04541858448704
        ],
        "geometry": "default",
        "id": "HYBRID_D8.6_D3.3"
      },
      {
        "horror": 3149.3004897658975,
        "dim": "HYBRID",
        "desc": "Dolor corrompe Muerte ancestral",
        "label": "Dolor corrompe Muerte ancestral",
        "position": [
          14.604145325870036,
          -414.1881007291273,
          -562.1055758901098
        ],
        "geometry": "default",
        "id": "HYBRID_D8.8_D4.7"
      }
    ],
    "edges": [
      {
        "weight": 1.0,
        "source": "CERO_ABSOLUTO",
        "target": "D1"
      },
      {
        "weight": 1.0,
        "source": "CERO_ABSOLUTO",
        "target": "D2"
      },
      {
        "weight": 1.0,
        "source": "CERO_ABSOLUTO",
        "target": "D3"
      },
      {
        "weight": 1.0,
        "source": "CERO_ABSOLUTO",
        "target": "D4"
      },
      {
        "weight": 1.0,
        "source": "CERO_ABSOLUTO",
        "target": "D5"
      },
      {
        "weight": 1.0,
        "source": "CERO_ABSOLUTO",
        "target": "D6"
      },
      {
        "weight": 1.0,
        "source": "CERO_ABSOLUTO",
        "target": "D7"
      },
      {
        "weight": 1.0,
        "source": "CERO_ABSOLUTO",
        "target": "D8"
      },
      {
        "weight": 1.0,
        "source": "CERO_ABSOLUTO",
        "target": "D9"
      },
      {
        "weight": 1.7071036106107325,
        "source": "D1",
        "target": "D1.1"
      },
      {
        "weight": 1.788330698172007,
        "source": "D1",
        "target": "D1.2"
      },
      {
        "weight": 1.747867928911805,
        "source": "D1",
        "target": "D1.3"
      },
      {
        "weight": 1.6645853989866153,
        "source": "D1",
        "target": "D1.4"
      },
      {
        "weight": 1.3728965667054802,
        "source": "D1",
        "target": "D1.5"
      },
      {
        "weight": 1.7313981353707448,
        "source": "D1",
        "target": "D1.6"
      },
      {
        "weight": 1.676376168994246,
        "source": "D1",
        "target": "D1.7"
      },
      {
        "weight": 1.7718704582261258,
        "source": "D1",
        "target": "D1.8"
      },
      {
        "weight": 1.0128397635248256,
        "label": "sinergia",
        "source": "D1.1",
        "target": "D7.6"
      },
      {
        "weight": 2.0,
        "source": "D1.1",
        "target": "HYBRID_D3.8_D1.1"
      },
      {
        "weight": 1.5811864515653031,
        "label": "sinergia",
        "source": "D1.3",
        "target": "D4.7"
      },
      {
        "weight": 2.0,
        "source": "D1.3",
        "target": "HYBRID_D1.3_D4.7"
      },
      {
        "weight": 1.4185066820521675,
        "label": "sinergia",
        "source": "D1.4",
        "target": "D4.7"
      },
      {
        "weight": 1.2316727391181144,
        "label": "sinergia",
        "source": "D1.8",
        "target": "D5.8"
      },
      {
        "weight": 1.8380113754906109,
        "source": "D2",
        "target": "D2.1"
      },
      {
        "weight": 1.5477649487201526,
        "source": "D2",
        "target": "D2.2"
      },
      {
        "weight": 1.6355195759631542,
        "source": "D2",
        "target": "D2.3"
      },
      {
        "weight": 1.4132496773746204,
        "source": "D2",
        "target": "D2.4"
      },
      {
        "weight": 1.7618908600590173,
        "source": "D2",
        "target": "D2.5"
      },
      {
        "weight": 1.5010767421101534,
        "source": "D2",
        "target": "D2.6"
      },
      {
        "weight": 1.507764512917008,
        "source": "D2",
        "target": "D2.7"
      },
      {
        "weight": 1.5013774276309295,
        "source": "D2",
        "target": "D2.8"
      },
      {
        "weight": 1.1050854457127266,
        "label": "sinergia",
        "source": "D2",
        "target": "D8.6"
      },
      {
        "weight": 1.3011897817088816,
        "label": "sinergia",
        "source": "D2.2",
        "target": "D4.7"
      },
      {
        "weight": 1.7035833332547705,
        "label": "sinergia",
        "source": "D2.4",
        "target": "D6.1"
      },
      {
        "weight": 2.0,
        "source": "D2.4",
        "target": "HYBRID_D2.4_D6.1"
      },
      {
        "weight": 2.0,
        "source": "D2.6",
        "target": "HYBRID_D8.5_D2.6"
      },
      {
        "weight": 1.1409980299419011,
        "label": "sinergia",
        "source": "D2.8",
        "target": "D1.3"
      },
      {
        "weight": 1.4709830097361696,
        "source": "D3",
        "target": "D3.1"
      },
      {
        "weight": 1.7828171135971878,
        "source": "D3",
        "target": "D3.2"
      },
      {
        "weight": 1.596284323155587,
        "source": "D3",
        "target": "D3.3"
      },
      {
        "weight": 1.4059435291074975,
        "source": "D3",
        "target": "D3.4"
      },
      {
        "weight": 1.4030784948022603,
        "source": "D3",
        "target": "D3.5"
      },
      {
        "weight": 1.6356282058952734,
        "source": "D3",
        "target": "D3.6"
      },
      {
        "weight": 1.4415771565681852,
        "source": "D3",
        "target": "D3.7"
      },
      {
        "weight": 1.5074754027592545,
        "source": "D3",
        "target": "D3.8"
      },
      {
        "weight": 1.4676031366852778,
        "label": "sinergia",
        "source": "D3",
        "target": "D9.8"
      },
      {
        "weight": 2.0,
        "source": "D3.3",
        "target": "HYBRID_D8.6_D3.3"
      },
      {
        "weight": 2.0,
        "source": "D3.5",
        "target": "HYBRID_D5.3_D3.5"
      },
      {
        "weight": 0.853703370751631,
        "label": "sinergia",
        "source": "D3.7",
        "target": "D7.6"
      },
      {
        "weight": 1.7764008039366819,
        "label": "sinergia",
        "source": "D3.8",
        "target": "D1.1"
      },
      {
        "weight": 2.0,
        "source": "D3.8",
        "target": "HYBRID_D3.8_D1.1"
      },
      {
        "weight": 1.5957218993073152,
        "source": "D4",
        "target": "D4.1"
      },
      {
        "weight": 1.7298248323793834,
        "source": "D4",
        "target": "D4.2"
      },
      {
        "weight": 1.8344237611848728,
        "source": "D4",
        "target": "D4.3"
      },
      {
        "weight": 1.7399264361396287,
        "source": "D4",
        "target": "D4.4"
      },
      {
        "weight": 1.7836707767770335,
        "source": "D4",
        "target": "D4.5"
      },
      {
        "weight": 1.8335444287983411,
        "source": "D4",
        "target": "D4.6"
      },
      {
        "weight": 1.5187197972733084,
        "source": "D4",
        "target": "D4.7"
      },
      {
        "weight": 1.6597039719187037,
        "source": "D4",
        "target": "D4.8"
      },
      {
        "weight": 1.0748643631432746,
        "label": "sinergia",
        "source": "D4",
        "target": "D5.6"
      },
      {
        "weight": 0.8477854989968021,
        "label": "sinergia",
        "source": "D4.1",
        "target": "D1.1"
      },
      {
        "weight": 1.4158779011449578,
        "label": "sinergia",
        "source": "D4.4",
        "target": "D8.4"
      },
      {
        "weight": 1.15477471076516,
        "label": "sinergia",
        "source": "D4.5",
        "target": "D2.8"
      },
      {
        "weight": 1.8709920440511656,
        "label": "sinergia",
        "source": "D4.6",
        "target": "D9.8"
      },
      {
        "weight": 2.0,
        "source": "D4.6",
        "target": "HYBRID_D4.6_D9.8"
      },
      {
        "weight": 2.0,
        "source": "D4.7",
        "target": "HYBRID_D1.3_D4.7"
      },
      {
        "weight": 2.0,
        "source": "D4.7",
        "target": "HYBRID_D8.8_D4.7"
      },
      {
        "weight": 1.5626070241446313,
        "source": "D5",
        "target": "D5.1"
      },
      {
        "weight": 1.4576772820453539,
        "source": "D5",
        "target": "D5.2"
      },
      {
        "weight": 1.3701788307931726,
        "source": "D5",
        "target": "D5.3"
      },
      {
        "weight": 1.5426743124038318,
        "source": "D5",
        "target": "D5.4"
      },
      {
        "weight": 1.7198142327927917,
        "source": "D5",
        "target": "D5.5"
      },
      {
        "weight": 1.6505965485786396,
        "source": "D5",
        "target": "D5.6"
      },
      {
        "weight": 1.6826654538249923,
        "source": "D5",
        "target": "D5.7"
      },
      {
        "weight": 1.7467928244620519,
        "source": "D5",
        "target": "D5.8"
      },
      {
        "weight": 2.0,
        "source": "D5.2",
        "target": "HYBRID_D7.7_D5.2"
      },
      {
        "weight": 1.629242386266307,
        "label": "sinergia",
        "source": "D5.3",
        "target": "D3.5"
      },
      {
        "weight": 2.0,
        "source": "D5.3",
        "target": "HYBRID_D5.3_D3.5"
      },
      {
        "weight": 1.6704243520352717,
        "label": "sinergia",
        "source": "D5.7",
        "target": "D8.7"
      },
      {
        "weight": 2.0,
        "source": "D5.7",
        "target": "HYBRID_D5.7_D8.7"
      },
      {
        "weight": 1.5798807575015879,
        "source": "D6",
        "target": "D6.1"
      },
      {
        "weight": 1.384758421827669,
        "source": "D6",
        "target": "D6.2"
      },
      {
        "weight": 1.7831628949202192,
        "source": "D6",
        "target": "D6.3"
      },
      {
        "weight": 1.8103949770250445,
        "source": "D6",
        "target": "D6.4"
      },
      {
        "weight": 1.4899054762344466,
        "source": "D6",
        "target": "D6.5"
      },
      {
        "weight": 1.525213449431948,
        "source": "D6",
        "target": "D6.6"
      },
      {
        "weight": 1.5725155389206467,
        "source": "D6",
        "target": "D6.7"
      },
      {
        "weight": 1.4129677187665588,
        "source": "D6",
        "target": "D6.8"
      },
      {
        "weight": 2.0,
        "source": "D6.1",
        "target": "HYBRID_D2.4_D6.1"
      },
      {
        "weight": 1.9932719180478309,
        "label": "sinergia",
        "source": "D6.1",
        "target": "D7.5"
      },
      {
        "weight": 2.0,
        "source": "D6.1",
        "target": "HYBRID_D6.1_D7.5"
      },
      {
        "weight": 0.8068640165491425,
        "label": "sinergia",
        "source": "D6.4",
        "target": "D8.5"
      },
      {
        "weight": 1.8846962797342557,
        "label": "sinergia",
        "source": "D6.7",
        "target": "D7.3"
      },
      {
        "weight": 2.0,
        "source": "D6.7",
        "target": "HYBRID_D6.7_D7.3"
      },
      {
        "weight": 1.3973901094630674,
        "label": "sinergia",
        "source": "D6.8",
        "target": "D7"
      },
      {
        "weight": 1.8380407286875338,
        "source": "D7",
        "target": "D7.1"
      },
      {
        "weight": 1.7460284651096243,
        "source": "D7",
        "target": "D7.2"
      },
      {
        "weight": 1.4219057266207487,
        "source": "D7",
        "target": "D7.3"
      },
      {
        "weight": 1.707883285564637,
        "source": "D7",
        "target": "D7.4"
      },
      {
        "weight": 1.7167331856882122,
        "source": "D7",
        "target": "D7.5"
      },
      {
        "weight": 1.4556894816223132,
        "source": "D7",
        "target": "D7.6"
      },
      {
        "weight": 1.4539364084439166,
        "source": "D7",
        "target": "D7.7"
      },
      {
        "weight": 1.3551205630948384,
        "source": "D7",
        "target": "D7.8"
      },
      {
        "weight": 2.0,
        "source": "D7.3",
        "target": "HYBRID_D6.7_D7.3"
      },
      {
        "weight": 1.3984644708691274,
        "label": "sinergia",
        "source": "D7.3",
        "target": "D3.3"
      },
      {
        "weight": 0.9933959876799886,
        "label": "sinergia",
        "source": "D7.4",
        "target": "D8.6"
      },
      {
        "weight": 2.0,
        "source": "D7.5",
        "target": "HYBRID_D6.1_D7.5"
      },
      {
        "weight": 1.5627677984957709,
        "label": "sinergia",
        "source": "D7.7",
        "target": "D5.2"
      },
      {
        "weight": 2.0,
        "source": "D7.7",
        "target": "HYBRID_D7.7_D5.2"
      },
      {
        "weight": 1.7372392813074806,
        "source": "D8",
        "target": "D8.1"
      },
      {
        "weight": 1.419562764806079,
        "source": "D8",
        "target": "D8.2"
      },
      {
        "weight": 1.8348778360373745,
        "source": "D8",
        "target": "D8.3"
      },
      {
        "weight": 1.3665846570867415,
        "source": "D8",
        "target": "D8.4"
      },
      {
        "weight": 1.819868591677794,
        "source": "D8",
        "target": "D8.5"
      },
      {
        "weight": 1.5774795657474874,
        "source": "D8",
        "target": "D8.6"
      },
      {
        "weight": 1.6933176073268137,
        "source": "D8",
        "target": "D8.7"
      },
      {
        "weight": 1.7317988748130317,
        "source": "D8",
        "target": "D8.8"
      },
      {
        "weight": 1.4503581557130034,
        "label": "sinergia",
        "source": "D8.2",
        "target": "D6.3"
      },
      {
        "weight": 0.8757358581493413,
        "label": "sinergia",
        "source": "D8.4",
        "target": "D3.4"
      },
      {
        "weight": 1.5411889836821207,
        "label": "sinergia",
        "source": "D8.5",
        "target": "D2.6"
      },
      {
        "weight": 2.0,
        "source": "D8.5",
        "target": "HYBRID_D8.5_D2.6"
      },
      {
        "weight": 1.8127398805256094,
        "label": "sinergia",
        "source": "D8.6",
        "target": "D3.3"
      },
      {
        "weight": 2.0,
        "source": "D8.6",
        "target": "HYBRID_D8.6_D3.3"
      },
      {
        "weight": 2.0,
        "source": "D8.7",
        "target": "HYBRID_D5.7_D8.7"
      },
      {
        "weight": 1.021277673188719,
        "label": "sinergia",
        "source": "D8.7",
        "target": "D2.1"
      },
      {
        "weight": 1.8789790716406904,
        "label": "sinergia",
        "source": "D8.8",
        "target": "D4.7"
      },
      {
        "weight": 2.0,
        "source": "D8.8",
        "target": "HYBRID_D8.8_D4.7"
      },
      {
        "weight": 1.3960598068338208,
        "source": "D9",
        "target": "D9.1"
      },
      {
        "weight": 1.5842177379435594,
        "source": "D9",
        "target": "D9.2"
      },
      {
        "weight": 1.5183916287177017,
        "source": "D9",
        "target": "D9.3"
      },
      {
        "weight": 1.6565457909938983,
        "source": "D9",
        "target": "D9.4"
      },
      {
        "weight": 1.681272290820357,
        "source": "D9",
        "target": "D9.5"
      },
      {
        "weight": 1.7849626497907787,
        "source": "D9",
        "target": "D9.6"
      },
      {
        "weight": 1.4463235341926897,
        "source": "D9",
        "target": "D9.7"
      },
      {
        "weight": 1.6224029441887007,
        "source": "D9",
        "target": "D9.8"
      },
      {
        "weight": 0.9522114115720024,
        "label": "sinergia",
        "source": "D9",
        "target": "D6.7"
      },
      {
        "weight": 0.9253814689606605,
        "label": "sinergia",
        "source": "D9.6",
        "target": "D4.1"
      },
      {
        "weight": 1.3685745101043245,
        "label": "sinergia",
        "source": "D9.7",
        "target": "D3.1"
      },
      {
        "weight": 2.0,
        "source": "D9.8",
        "target": "HYBRID_D4.6_D9.8"
      }
    ]
  },
  "analisis": {
    "horror_total": 185568.27698289254,
    "horror_promedio": 1974.1306062009844,
    "nodos_mas_horribles": [
      [
        "HYBRID_D5.7_D8.7",
        3388.81425063938
      ],
      [
        "HYBRID_D4.6_D9.8",
        3356.7867004211794
      ],
      [
        "HYBRID_D3.8_D1.1",
        3208.5439142799264
      ],
      [
        "HYBRID_D6.1_D7.5",
        3181.6552161427153
      ],
      [
        "HYBRID_D8.6_D3.3",
        3162.6534210495374
      ],
      [
        "HYBRID_D8.8_D4.7",
        3149.3004897658975
      ],
      [
        "HYBRID_D8.5_D2.6",
        2843.1187552756555
      ],
      [
        "HYBRID_D6.7_D7.3",
        2802.6951253691086
      ],
      [
        "HYBRID_D2.4_D6.1",
        2769.209288853247
      ],
      [
        "HYBRID_D1.3_D4.7",
        2766.920026329164
      ]
    ],
    "clusters": [
      {
        "dim": 0,
        "horror_total": 1382.1049773286354,
        "node_count": 1,
        "mini_singularity": {
          "size": 5,
          "mass": 9.214033182190903
        }
      },
      {
        "dim": 1,
        "horror_total": 18606.489222218675,
        "node_count": 9,
        "mini_singularity": {
          "size": 5,
          "mass": 124.04326148145783
        }
      },
      {
        "dim": 2,
        "horror_total": 15412.689984829858,
        "node_count": 9,
        "mini_singularity": {
          "size": 5,
          "mass": 102.75126656553239
        }
      },
      {
        "dim": 3,
        "horror_total": 15286.415163490678,
        "node_count": 9,
        "mini_singularity": {
          "size": 5,
          "mass": 101.90943442327118
        }
      },
      {
        "dim": 4,
        "horror_total": 14249.251713927317,
        "node_count": 9,
        "mini_singularity": {
          "size": 5,
          "mass": 94.99501142618212
        }
      },
      {
        "dim": 5,
        "horror_total": 18263.537498851732,
        "node_count": 9,
        "mini_singularity": {
          "size": 5,
          "mass": 121.75691665901155
        }
      },
      {
        "dim": 6,
        "horror_total": 17406.357886833623,
        "node_count": 9,
        "mini_singularity": {
          "size": 5,
          "mass": 116.04238591222415
        }
      },
      {
        "dim": 7,
        "horror_total": 13505.12822829592,
        "node_count": 9,
        "mini_singularity": {
          "size": 5,
          "mass": 90.03418818863946
        }
      },
      {
        "dim": 8,
        "horror_total": 18182.92016702466,
        "node_count": 9,
        "mini_singularity": {
          "size": 5,
          "mass": 121.2194677801644
        }
      },
      {
        "dim": 9,
        "horror_total": 17601.117207188163,
        "node_count": 9,
        "mini_singularity": {
          "size": 5,
          "mass": 117.34078138125442
        }
      },
      {
        "dim": "HYBRID",
        "horror_total": 35672.26493290329,
        "node_count": 12,
        "mini_singularity": {
          "size": 5,
          "mass": 237.81509955268857
        }
      }
    ],
    "total_nodos": 94,
    "total_edges": 139,
    "modo": "MODO BESTIA",
    "modo_info": {
      "threshold": 90000,
      "desc": "👹 Bestia total – risa loca, Φ eliminado",
      "color": "#ff0000",
      "emoji": "👹",
      "physics": {
        "gravity": -50000,
        "spring_length": 30,
        "spring_strength": 0.15
      },
      "node_shape": "star",
      "geometry": "chaotic_burst"
    },
    "timestamp": "2026-01-20T20:31:16.354814"
  },
  "version": "v4.1"
}