{
  "nodes": [
    {
      "id": "CERO_ABSOLUTO",
      "horror": 1317.6249986397097,
      "dim": 0,
      "timestamp": "2026-01-20T20:31:13.776506",
      "desc": "El abismo total",
      "label": "CERO ABSOLUTO",
      "position": [
        0,
        0,
        0
      ],
      "shape": "sphere",
      "geometry": "blackhole"
    },
    {
      "id": "D1",
      "horror": 1190.6064574952402,
      "dim": 1,
      "timestamp": "2026-01-20T20:31:13.776506",
      "desc": "Traici\u00f3n absoluta (socios, instituciones, familia)",
      "label": "D1: Traici\u00f3n absoluta (socios, instituciones, familia)",
      "position": [
        -78.07053457065933,
        -6.303441971536813,
        -679.0046934477809
      ],
      "shape": "sphere",
      "geometry": "default"
    },
    {
      "id": "D1.1",
      "horror": 1576.4353535219127,
      "dim": 1,
      "sub_level": 1,
      "timestamp": "2026-01-20T20:31:13.776506",
      "desc": "Traici\u00f3n absoluta (socios, instituciones, familia) agravado x1.64",
      "label": "D1.1",
      "position": [
        -141.18033283847177,
        -63.662104335009374,
        -716.5418434962147
      ],
      "shape": "dot",
      "geometry": "default"
    },
    {
      "id": "D1.2",
      "horror": 1761.8888951395893,
      "dim": 1,
      "sub_level": 2,
      "timestamp": "2026-01-20T20:31:13.776506",
      "desc": "Traici\u00f3n absoluta (socios, instituciones, familia) agravado x1.76",
      "label": "D1.2",
      "position": [
        62.579873541534596,
        80.3609237778042,
        -714.8001453018286
      ],
      "shape": "dot",
      "geometry": "default"
    },
    {
      "id": "D1.3",
      "horror": 1489.39771614503,
      "dim": 1,
      "sub_level": 3,
      "timestamp": "2026-01-20T20:31:13.776506",
      "desc": "Traici\u00f3n absoluta (socios, instituciones, familia) agravado x1.43",
      "label": "D1.3",
      "position": [
        -63.85423155157014,
        77.67876170624464,
        -738.9915814277092
      ],
      "shape": "dot",
      "geometry": "default"
    },
    {
      "id": "D1.4",
      "horror": 1605.3844415828037,
      "dim": 1,
      "sub_level": 4,
      "timestamp": "2026-01-20T20:31:13.776506",
      "desc": "Traici\u00f3n absoluta (socios, instituciones, familia) agravado x1.68",
      "label": "D1.4",
      "position": [
        -139.1208255986692,
        -146.51466264945603,
        -544.3781203238868
      ],
      "shape": "dot",
      "geometry": "default"
    },
    {
      "id": "D1.5",
      "horror": 1430.055626751989,
      "dim": 1,
      "sub_level": 5,
      "timestamp": "2026-01-20T20:31:13.776506",
      "desc": "Traici\u00f3n absoluta (socios, instituciones, familia) agravado x1.43",
      "label": "D1.5",
      "position": [
        -144.40449618828313,
        16.048912856343634,
        -662.8389325671155
      ],
      "shape": "dot",
      "geometry": "default"
    },
    {
      "id": "D1.6",
      "horror": 1381.84565538857,
      "dim": 1,
      "sub_level": 6,
      "timestamp": "2026-01-20T20:31:13.776506",
      "desc": "Traici\u00f3n absoluta (socios, instituciones, familia) agravado x1.39",
      "label": "D1.6",
      "position": [
        -178.63282224367595,
        61.96544698962987,
        -792.1047472616171
      ],
      "shape": "dot",
      "geometry": "default"
    },
    {
      "id": "D1.7",
      "horror": 1645.3686978018582,
      "dim": 1,
      "sub_level": 7,
      "timestamp": "2026-01-20T20:31:13.776506",
      "desc": "Traici\u00f3n absoluta (socios, instituciones, familia) agravado x1.53",
      "label": "D1.7",
      "position": [
        -223.7914819433562,
        -1.467180844916271,
        -756.915710832756
      ],
      "shape": "dot",
      "geometry": "default"
    },
    {
      "id": "D1.8",
      "horror": 1660.485051565426,
      "dim": 1,
      "sub_level": 8,
      "timestamp": "2026-01-20T20:31:13.776506",
      "desc": "Traici\u00f3n absoluta (socios, instituciones, familia) agravado x1.60",
      "label": "D1.8",
      "position": [
        -116.6560815349656,
        -45.08374674439709,
        -701.584782256702
      ],
      "shape": "dot",
      "geometry": "default"
    },
    {
      "id": "D2",
      "horror": 1344.7352748831638,
      "dim": 2,
      "timestamp": "2026-01-20T20:31:13.776506",
      "desc": "Colapso econ\u00f3mico / pobreza perpetua / mendicidad",
      "label": "D2: Colapso econ\u00f3mico / pobreza perpetua / mendicidad",
      "position": [
        159.50560453682192,
        67.61676319944843,
        550.1623551872192
      ],
      "shape": "sphere",
      "geometry": "default"
    },
    {
      "id": "D2.1",
      "horror": 1573.2496540196646,
      "dim": 2,
      "sub_level": 1,
      "timestamp": "2026-01-20T20:31:13.776506",
      "desc": "Colapso econ\u00f3mico / pobreza perpetua / mendicidad agravado x1.49",
      "label": "D2.1",
      "position": [
        34.334099236214584,
        115.11800848571676,
        466.4159765660047
      ],
      "shape": "dot",
      "geometry": "default"
    },
    {
      "id": "D2.2",
      "horror": 1969.2487032726817,
      "dim": 2,
      "sub_level": 2,
      "timestamp": "2026-01-20T20:31:13.776506",
      "desc": "Colapso econ\u00f3mico / pobreza perpetua / mendicidad agravado x1.76",
      "label": "D2.2",
      "position": [
        128.7368754425063,
        120.23496623686583,
        672.6742191901008
      ],
      "shape": "dot",
      "geometry": "default"
    },
    {
      "id": "D2.3",
      "horror": 1820.7816558420288,
      "dim": 2,
      "sub_level": 3,
      "timestamp": "2026-01-20T20:31:13.776506",
      "desc": "Colapso econ\u00f3mico / pobreza perpetua / mendicidad agravado x1.69",
      "label": "D2.3",
      "position": [
        291.8817811455257,
        209.0705851714264,
        573.520444145497
      ],
      "shape": "dot",
      "geometry": "default"
    },
    {
      "id": "D2.4",
      "horror": 1929.8168587635537,
      "dim": 2,
      "sub_level": 4,
      "timestamp": "2026-01-20T20:31:13.776506",
      "desc": "Colapso econ\u00f3mico / pobreza perpetua / mendicidad agravado x1.84",
      "label": "D2.4",
      "position": [
        89.73682787473997,
        85.19587305931202,
        404.0209070697552
      ],
      "shape": "dot",
      "geometry": "default"
    },
    {
      "id": "D2.5",
      "horror": 1916.2639368435985,
      "dim": 2,
      "sub_level": 5,
      "timestamp": "2026-01-20T20:31:13.776506",
      "desc": "Colapso econ\u00f3mico / pobreza perpetua / mendicidad agravado x1.72",
      "label": "D2.5",
      "position": [
        274.0931193624826,
        -76.5262280144839,
        496.5820794946536
      ],
      "shape": "dot",
      "geometry": "default"
    },
    {
      "id": "D2.6",
      "horror": 1608.1031211133363,
      "dim": 2,
      "sub_level": 6,
      "timestamp": "2026-01-20T20:31:13.776506",
      "desc": "Colapso econ\u00f3mico / pobreza perpetua / mendicidad agravado x1.36",
      "label": "D2.6",
      "position": [
        244.67229717333862,
        95.46224928058706,
        570.061307729534
      ],
      "shape": "dot",
      "geometry": "default"
    },
    {
      "id": "D2.7",
      "horror": 1879.6081804215028,
      "dim": 2,
      "sub_level": 7,
      "timestamp": "2026-01-20T20:31:13.776506",
      "desc": "Colapso econ\u00f3mico / pobreza perpetua / mendicidad agravado x1.80",
      "label": "D2.7",
      "position": [
        183.971550685646,
        156.1359860879188,
        578.1905706407094
      ],
      "shape": "dot",
      "geometry": "default"
    },
    {
      "id": "D2.8",
      "horror": 1881.4722901114853,
      "dim": 2,
      "sub_level": 8,
      "timestamp": "2026-01-20T20:31:13.776506",
      "desc": "Colapso econ\u00f3mico / pobreza perpetua / mendicidad agravado x1.69",
      "label": "D2.8",
      "position": [
        134.71658600700994,
        -14.203963121609888,
        485.4598368080202
      ],
      "shape": "dot",
      "geometry": "default"
    },
    {
      "id": "D3",
      "horror": 1214.7020267109338,
      "dim": 3,
      "timestamp": "2026-01-20T20:31:13.776506",
      "desc": "Aislamiento total (nadie real, nakamas falsos)",
      "label": "D3: Aislamiento total (nadie real, nakamas falsos)",
      "position": [
        595.7380994880687,
        15.78361787272604,
        -635.2776887987447
      ],
      "shape": "sphere",
      "geometry": "default"
    },
    {
      "id": "D3.1",
      "horror": 1618.3731140237699,
      "dim": 3,
      "sub_level": 1,
      "timestamp": "2026-01-20T20:31:13.776506",
      "desc": "Aislamiento total (nadie real, nakamas falsos) agravado x1.68",
      "label": "D3.1",
      "position": [
        465.1283237258413,
        138.62651705325345,
        -614.1691973295949
      ],
      "shape": "dot",
      "geometry": "default"
    },
    {
      "id": "D3.2",
      "horror": 1599.3684942499792,
      "dim": 3,
      "sub_level": 2,
      "timestamp": "2026-01-20T20:31:13.776506",
      "desc": "Aislamiento total (nadie real, nakamas falsos) agravado x1.73",
      "label": "D3.2",
      "position": [
        727.8952716819042,
        -121.23999418173088,
        -769.2810905152646
      ],
      "shape": "dot",
      "geometry": "default"
    },
    {
      "id": "D3.3",
      "horror": 1669.2038577554044,
      "dim": 3,
      "sub_level": 3,
      "timestamp": "2026-01-20T20:31:13.776506",
      "desc": "Aislamiento total (nadie real, nakamas falsos) agravado x1.71",
      "label": "D3.3",
      "position": [
        610.1521147765383,
        64.17409765552966,
        -683.1168564472825
      ],
      "shape": "dot",
      "geometry": "default"
    },
    {
      "id": "D3.4",
      "horror": 1695.16263601889,
      "dim": 3,
      "sub_level": 4,
      "timestamp": "2026-01-20T20:31:13.776506",
      "desc": "Aislamiento total (nadie real, nakamas falsos) agravado x1.55",
      "label": "D3.4",
      "position": [
        628.688583804931,
        156.13120414535052,
        -760.2152639898328
      ],
      "shape": "dot",
      "geometry": "default"
    },
    {
      "id": "D3.5",
      "horror": 1351.7078615408998,
      "dim": 3,
      "sub_level": 5,
      "timestamp": "2026-01-20T20:31:13.776506",
      "desc": "Aislamiento total (nadie real, nakamas falsos) agravado x1.42",
      "label": "D3.5",
      "position": [
        570.5958880884875,
        85.49813191909146,
        -746.8074633163365
      ],
      "shape": "dot",
      "geometry": "default"
    },
    {
      "id": "D3.6",
      "horror": 1699.3443252396728,
      "dim": 3,
      "sub_level": 6,
      "timestamp": "2026-01-20T20:31:13.776506",
      "desc": "Aislamiento total (nadie real, nakamas falsos) agravado x1.80",
      "label": "D3.6",
      "position": [
        511.5824325402503,
        -130.29304274255614,
        -731.5106122300956
      ],
      "shape": "dot",
      "geometry": "default"
    },
    {
      "id": "D3.7",
      "horror": 1563.1553014939286,
      "dim": 3,
      "sub_level": 7,
      "timestamp": "2026-01-20T20:31:13.776506",
      "desc": "Aislamiento total (nadie real, nakamas falsos) agravado x1.55",
      "label": "D3.7",
      "position": [
        466.7191694348679,
        99.33953418068245,
        -702.1213622730303
      ],
      "shape": "dot",
      "geometry": "default"
    },
    {
      "id": "D3.8",
      "horror": 1489.571909100563,
      "dim": 3,
      "sub_level": 8,
      "timestamp": "2026-01-20T20:31:13.776506",
      "desc": "Aislamiento total (nadie real, nakamas falsos) agravado x1.45",
      "label": "D3.8",
      "position": [
        706.3221203931028,
        -0.883543059631478,
        -766.2825301713328
      ],
      "shape": "dot",
      "geometry": "default"
    },
    {
      "id": "D4",
      "horror": 1327.922425325536,
      "dim": 4,
      "timestamp": "2026-01-20T20:31:13.776506",
      "desc": "Muerte cercana o p\u00e9rdida irreparable (hijo, libertad)",
      "label": "D4: Muerte cercana o p\u00e9rdida irreparable (hijo, libertad)",
      "position": [
        347.11552083435186,
        -590.5895405383208,
        -597.5856134927578
      ],
      "shape": "sphere",
      "geometry": "default"
    },
    {
      "id": "D4.1",
      "horror": 2063.7735344201346,
      "dim": 4,
      "sub_level": 1,
      "timestamp": "2026-01-20T20:31:13.776506",
      "desc": "Muerte cercana o p\u00e9rdida irreparable (hijo, libertad) agravado x1.77",
      "label": "D4.1",
      "position": [
        478.3092181138835,
        -603.042742917035,
        -471.0554522411695
      ],
      "shape": "dot",
      "geometry": "default"
    },
    {
      "id": "D4.2",
      "horror": 1893.2629296174237,
      "dim": 4,
      "sub_level": 2,
      "timestamp": "2026-01-20T20:31:13.776506",
      "desc": "Muerte cercana o p\u00e9rdida irreparable (hijo, libertad) agravado x1.61",
      "label": "D4.2",
      "position": [
        381.6553867550783,
        -450.12750788659525,
        -448.0358804565182
      ],
      "shape": "dot",
      "geometry": "default"
    },
    {
      "id": "D4.3",
      "horror": 2004.5641297669101,
      "dim": 4,
      "sub_level": 3,
      "timestamp": "2026-01-20T20:31:13.776506",
      "desc": "Muerte cercana o p\u00e9rdida irreparable (hijo, libertad) agravado x1.74",
      "label": "D4.3",
      "position": [
        235.37461151410437,
        -575.02783431314,
        -744.3244699868499
      ],
      "shape": "dot",
      "geometry": "default"
    },
    {
      "id": "D4.4",
      "horror": 2075.6310637201605,
      "dim": 4,
      "sub_level": 4,
      "timestamp": "2026-01-20T20:31:13.776506",
      "desc": "Muerte cercana o p\u00e9rdida irreparable (hijo, libertad) agravado x1.80",
      "label": "D4.4",
      "position": [
        296.0548109161486,
        -498.7723541438083,
        -533.9415166869074
      ],
      "shape": "dot",
      "geometry": "default"
    },
    {
      "id": "D4.5",
      "horror": 1728.347981205848,
      "dim": 4,
      "sub_level": 5,
      "timestamp": "2026-01-20T20:31:13.776506",
      "desc": "Muerte cercana o p\u00e9rdida irreparable (hijo, libertad) agravado x1.38",
      "label": "D4.5",
      "position": [
        386.79880399254387,
        -572.5064718415105,
        -653.7639415317507
      ],
      "shape": "dot",
      "geometry": "default"
    },
    {
      "id": "D4.6",
      "horror": 1558.2309110333044,
      "dim": 4,
      "sub_level": 6,
      "timestamp": "2026-01-20T20:31:13.776506",
      "desc": "Muerte cercana o p\u00e9rdida irreparable (hijo, libertad) agravado x1.39",
      "label": "D4.6",
      "position": [
        288.72137850340073,
        -516.8223997842151,
        -682.9595388992101
      ],
      "shape": "dot",
      "geometry": "default"
    },
    {
      "id": "D4.7",
      "horror": 2006.4018748208625,
      "dim": 4,
      "sub_level": 7,
      "timestamp": "2026-01-20T20:31:13.776506",
      "desc": "Muerte cercana o p\u00e9rdida irreparable (hijo, libertad) agravado x1.81",
      "label": "D4.7",
      "position": [
        304.837805468954,
        -444.317327533618,
        -663.4335931494999
      ],
      "shape": "dot",
      "geometry": "default"
    },
    {
      "id": "D4.8",
      "horror": 1763.1752989108247,
      "dim": 4,
      "sub_level": 8,
      "timestamp": "2026-01-20T20:31:13.776506",
      "desc": "Muerte cercana o p\u00e9rdida irreparable (hijo, libertad) agravado x1.40",
      "label": "D4.8",
      "position": [
        259.1334160128712,
        -554.6244070301087,
        -742.3535719096565
      ],
      "shape": "dot",
      "geometry": "default"
    },
    {
      "id": "D5",
      "horror": 1168.6460569052167,
      "dim": 5,
      "timestamp": "2026-01-20T20:31:13.776506",
      "desc": "Colapso cognitivo irreversible (f\u00e1rmacos, internaci\u00f3n)",
      "label": "D5: Colapso cognitivo irreversible (f\u00e1rmacos, internaci\u00f3n)",
      "position": [
        -51.99513335850975,
        657.0560642751445,
        376.0539076781831
      ],
      "shape": "sphere",
      "geometry": "default"
    },
    {
      "id": "D5.1",
      "horror": 1742.7250113742264,
      "dim": 5,
      "sub_level": 1,
      "timestamp": "2026-01-20T20:31:13.776506",
      "desc": "Colapso cognitivo irreversible (f\u00e1rmacos, internaci\u00f3n) agravado x1.81",
      "label": "D5.1",
      "position": [
        -27.954114737109848,
        738.1415414000058,
        302.1025375925152
      ],
      "shape": "dot",
      "geometry": "default"
    },
    {
      "id": "D5.2",
      "horror": 1600.3783258534372,
      "dim": 5,
      "sub_level": 2,
      "timestamp": "2026-01-20T20:31:13.776506",
      "desc": "Colapso cognitivo irreversible (f\u00e1rmacos, internaci\u00f3n) agravado x1.56",
      "label": "D5.2",
      "position": [
        70.87585542813008,
        717.5433679042007,
        493.26975944178673
      ],
      "shape": "dot",
      "geometry": "default"
    },
    {
      "id": "D5.3",
      "horror": 1661.6601418097418,
      "dim": 5,
      "sub_level": 3,
      "timestamp": "2026-01-20T20:31:13.776506",
      "desc": "Colapso cognitivo irreversible (f\u00e1rmacos, internaci\u00f3n) agravado x1.69",
      "label": "D5.3",
      "position": [
        45.73781416444973,
        734.6654689461886,
        327.144548110018
      ],
      "shape": "dot",
      "geometry": "default"
    },
    {
      "id": "D5.4",
      "horror": 1536.9944500604208,
      "dim": 5,
      "sub_level": 4,
      "timestamp": "2026-01-20T20:31:13.776506",
      "desc": "Colapso cognitivo irreversible (f\u00e1rmacos, internaci\u00f3n) agravado x1.62",
      "label": "D5.4",
      "position": [
        67.4549759424304,
        662.7644615294248,
        424.30745156206535
      ],
      "shape": "dot",
      "geometry": "default"
    },
    {
      "id": "D5.5",
      "horror": 1391.1136834284719,
      "dim": 5,
      "sub_level": 5,
      "timestamp": "2026-01-20T20:31:13.776506",
      "desc": "Colapso cognitivo irreversible (f\u00e1rmacos, internaci\u00f3n) agravado x1.46",
      "label": "D5.5",
      "position": [
        55.2028420004097,
        728.3416714638051,
        330.3692723515418
      ],
      "shape": "dot",
      "geometry": "default"
    },
    {
      "id": "D5.6",
      "horror": 1706.266172913979,
      "dim": 5,
      "sub_level": 6,
      "timestamp": "2026-01-20T20:31:13.776506",
      "desc": "Colapso cognitivo irreversible (f\u00e1rmacos, internaci\u00f3n) agravado x1.69",
      "label": "D5.6",
      "position": [
        -108.96851616469424,
        598.97383343257,
        255.93323707782724
      ],
      "shape": "dot",
      "geometry": "default"
    },
    {
      "id": "D5.7",
      "horror": 1581.2384003389354,
      "dim": 5,
      "sub_level": 7,
      "timestamp": "2026-01-20T20:31:13.776506",
      "desc": "Colapso cognitivo irreversible (f\u00e1rmacos, internaci\u00f3n) agravado x1.66",
      "label": "D5.7",
      "position": [
        -7.142814438751287,
        625.4746939066475,
        427.08565997835746
      ],
      "shape": "dot",
      "geometry": "default"
    },
    {
      "id": "D5.8",
      "horror": 1538.2548494829032,
      "dim": 5,
      "sub_level": 8,
      "timestamp": "2026-01-20T20:31:13.776506",
      "desc": "Colapso cognitivo irreversible (f\u00e1rmacos, internaci\u00f3n) agravado x1.59",
      "label": "D5.8",
      "position": [
        -186.12569318966052,
        515.3929585533115,
        288.19136773109153
      ],
      "shape": "dot",
      "geometry": "default"
    },
    {
      "id": "D6",
      "horror": 1051.0285671580546,
      "dim": 6,
      "timestamp": "2026-01-20T20:31:13.776506",
      "desc": "Vac\u00edo existencial / p\u00e9rdida prop\u00f3sito (33 a\u00f1os tristeza)",
      "label": "D6: Vac\u00edo existencial / p\u00e9rdida prop\u00f3sito (33 a\u00f1os tristeza)",
      "position": [
        -733.8596582820273,
        -641.7524905044694,
        228.860172365602
      ],
      "shape": "sphere",
      "geometry": "default"
    },
    {
      "id": "D6.1",
      "horror": 1172.6785935842058,
      "dim": 6,
      "sub_level": 1,
      "timestamp": "2026-01-20T20:31:13.776506",
      "desc": "Vac\u00edo existencial / p\u00e9rdida prop\u00f3sito (33 a\u00f1os tristeza) agravado x1.40",
      "label": "D6.1",
      "position": [
        -865.3983359562358,
        -700.1922802735719,
        317.31335727002624
      ],
      "shape": "dot",
      "geometry": "default"
    },
    {
      "id": "D6.2",
      "horror": 1424.1164646181753,
      "dim": 6,
      "sub_level": 2,
      "timestamp": "2026-01-20T20:31:13.776506",
      "desc": "Vac\u00edo existencial / p\u00e9rdida prop\u00f3sito (33 a\u00f1os tristeza) agravado x1.70",
      "label": "D6.2",
      "position": [
        -848.3899787735955,
        -727.8097243260936,
        233.54847544906107
      ],
      "shape": "dot",
      "geometry": "default"
    },
    {
      "id": "D6.3",
      "horror": 1194.649290415847,
      "dim": 6,
      "sub_level": 3,
      "timestamp": "2026-01-20T20:31:13.776506",
      "desc": "Vac\u00edo existencial / p\u00e9rdida prop\u00f3sito (33 a\u00f1os tristeza) agravado x1.42",
      "label": "D6.3",
      "position": [
        -607.9482784659851,
        -703.4790287612302,
        205.66627454913794
      ],
      "shape": "dot",
      "geometry": "default"
    },
    {
      "id": "D6.4",
      "horror": 1423.6994428240507,
      "dim": 6,
      "sub_level": 4,
      "timestamp": "2026-01-20T20:31:13.776506",
      "desc": "Vac\u00edo existencial / p\u00e9rdida prop\u00f3sito (33 a\u00f1os tristeza) agravado x1.75",
      "label": "D6.4",
      "position": [
        -654.4934147677097,
        -623.2545055645685,
        321.4654278038661
      ],
      "shape": "dot",
      "geometry": "default"
    },
    {
      "id": "D6.5",
      "horror": 1212.9420130057113,
      "dim": 6,
      "sub_level": 5,
      "timestamp": "2026-01-20T20:31:13.776506",
      "desc": "Vac\u00edo existencial / p\u00e9rdida prop\u00f3sito (33 a\u00f1os tristeza) agravado x1.44",
      "label": "D6.5",
      "position": [
        -750.9629404351535,
        -755.0572563720661,
        326.47698493110147
      ],
      "shape": "dot",
      "geometry": "default"
    },
    {
      "id": "D6.6",
      "horror": 1206.8873181095503,
      "dim": 6,
      "sub_level": 6,
      "timestamp": "2026-01-20T20:31:13.776506",
      "desc": "Vac\u00edo existencial / p\u00e9rdida prop\u00f3sito (33 a\u00f1os tristeza) agravado x1.37",
      "label": "D6.6",
      "position": [
        -883.3368809430075,
        -606.2755550461204,
        282.80556320482026
      ],
      "shape": "dot",
      "geometry": "default"
    },
    {
      "id": "D6.7",
      "horror": 1252.9355694741757,
      "dim": 6,
      "sub_level": 7,
      "timestamp": "2026-01-20T20:31:13.776506",
      "desc": "Vac\u00edo existencial / p\u00e9rdida prop\u00f3sito (33 a\u00f1os tristeza) agravado x1.55",
      "label": "D6.7",
      "position": [
        -836.351631732924,
        -532.5221470703151,
        363.0417923703097
      ],
      "shape": "dot",
      "geometry": "default"
    },
    {
      "id": "D6.8",
      "horror": 1428.4884818339904,
      "dim": 6,
      "sub_level": 8,
      "timestamp": "2026-01-20T20:31:13.776506",
      "desc": "Vac\u00edo existencial / p\u00e9rdida prop\u00f3sito (33 a\u00f1os tristeza) agravado x1.66",
      "label": "D6.8",
      "position": [
        -630.7674404486793,
        -618.600754496648,
        171.46113516229647
      ],
      "shape": "dot",
      "geometry": "default"
    },
    {
      "id": "D7",
      "horror": 1210.0605747281031,
      "dim": 7,
      "timestamp": "2026-01-20T20:31:13.776506",
      "desc": "Humillaci\u00f3n p\u00fablica perpetua (desprecio, rechazo ancestral)",
      "label": "D7: Humillaci\u00f3n p\u00fablica perpetua (desprecio, rechazo ancestral)",
      "position": [
        4.402925723777116,
        -671.3760288637893,
        -12.52174084253636
      ],
      "shape": "sphere",
      "geometry": "default"
    },
    {
      "id": "D7.1",
      "horror": 1553.6040951259358,
      "dim": 7,
      "sub_level": 1,
      "timestamp": "2026-01-20T20:31:13.776506",
      "desc": "Humillaci\u00f3n p\u00fablica perpetua (desprecio, rechazo ancestral) agravado x1.67",
      "label": "D7.1",
      "position": [
        -32.43555816422321,
        -571.3325490690979,
        107.44312957467815
      ],
      "shape": "dot",
      "geometry": "default"
    },
    {
      "id": "D7.2",
      "horror": 1447.6453499849192,
      "dim": 7,
      "sub_level": 2,
      "timestamp": "2026-01-20T20:31:13.776506",
      "desc": "Humillaci\u00f3n p\u00fablica perpetua (desprecio, rechazo ancestral) agravado x1.48",
      "label": "D7.2",
      "position": [
        -136.26316766459033,
        -661.9986520111482,
        -118.64255145058914
      ],
      "shape": "dot",
      "geometry": "default"
    },
    {
      "id": "D7.3",
      "horror": 1545.0492603296404,
      "dim": 7,
      "sub_level": 3,
      "timestamp": "2026-01-20T20:31:13.776506",
      "desc": "Humillaci\u00f3n p\u00fablica perpetua (desprecio, rechazo ancestral) agravado x1.39",
      "label": "D7.3",
      "position": [
        -54.65968410872824,
        -612.3776266280828,
        -29.766368475470045
      ],
      "shape": "dot",
      "geometry": "default"
    },
    {
      "id": "D7.4",
      "horror": 1460.6201071290677,
      "dim": 7,
      "sub_level": 4,
      "timestamp": "2026-01-20T20:31:13.776506",
      "desc": "Humillaci\u00f3n p\u00fablica perpetua (desprecio, rechazo ancestral) agravado x1.41",
      "label": "D7.4",
      "position": [
        -122.56690592305326,
        -588.023165389013,
        -112.57778514306595
      ],
      "shape": "dot",
      "geometry": "default"
    },
    {
      "id": "D7.5",
      "horror": 1739.398851364228,
      "dim": 7,
      "sub_level": 5,
      "timestamp": "2026-01-20T20:31:13.776506",
      "desc": "Humillaci\u00f3n p\u00fablica perpetua (desprecio, rechazo ancestral) agravado x1.58",
      "label": "D7.5",
      "position": [
        -115.97557093514962,
        -764.8064382159425,
        -37.39807784830934
      ],
      "shape": "dot",
      "geometry": "default"
    },
    {
      "id": "D7.6",
      "horror": 1729.4646280634126,
      "dim": 7,
      "sub_level": 6,
      "timestamp": "2026-01-20T20:31:13.776506",
      "desc": "Humillaci\u00f3n p\u00fablica perpetua (desprecio, rechazo ancestral) agravado x1.79",
      "label": "D7.6",
      "position": [
        78.89167536324416,
        -544.1191183376884,
        -64.16138435865835
      ],
      "shape": "dot",
      "geometry": "default"
    },
    {
      "id": "D7.7",
      "horror": 1348.4848002059996,
      "dim": 7,
      "sub_level": 7,
      "timestamp": "2026-01-20T20:31:13.776506",
      "desc": "Humillaci\u00f3n p\u00fablica perpetua (desprecio, rechazo ancestral) agravado x1.37",
      "label": "D7.7",
      "position": [
        120.3640966402753,
        -551.7541639777082,
        5.1460621203898995
      ],
      "shape": "dot",
      "geometry": "default"
    },
    {
      "id": "D7.8",
      "horror": 1718.8862931044478,
      "dim": 7,
      "sub_level": 8,
      "timestamp": "2026-01-20T20:31:13.776506",
      "desc": "Humillaci\u00f3n p\u00fablica perpetua (desprecio, rechazo ancestral) agravado x1.66",
      "label": "D7.8",
      "position": [
        -81.37881196332793,
        -522.2709648823134,
        -92.95559058716124
      ],
      "shape": "dot",
      "geometry": "default"
    },
    {
      "id": "D8",
      "horror": 1098.595992372601,
      "dim": 8,
      "timestamp": "2026-01-20T20:31:13.776506",
      "desc": "Dolor cr\u00f3nico / enfermedad inducida (iatrogenia sistema)",
      "label": "D8: Dolor cr\u00f3nico / enfermedad inducida (iatrogenia sistema)",
      "position": [
        -222.56792059468557,
        -3.104563747936936,
        -716.1072441055494
      ],
      "shape": "sphere",
      "geometry": "default"
    },
    {
      "id": "D8.1",
      "horror": 1530.8273006872732,
      "dim": 8,
      "sub_level": 1,
      "timestamp": "2026-01-20T20:31:13.776506",
      "desc": "Dolor cr\u00f3nico / enfermedad inducida (iatrogenia sistema) agravado x1.56",
      "label": "D8.1",
      "position": [
        -360.97628131805857,
        -5.4833464092041595,
        -639.8483725793504
      ],
      "shape": "dot",
      "geometry": "default"
    },
    {
      "id": "D8.2",
      "horror": 1369.5200126242812,
      "dim": 8,
      "sub_level": 2,
      "timestamp": "2026-01-20T20:31:13.776506",
      "desc": "Dolor cr\u00f3nico / enfermedad inducida (iatrogenia sistema) agravado x1.36",
      "label": "D8.2",
      "position": [
        -116.76676132358767,
        -57.5788234107732,
        -805.1127682009635
      ],
      "shape": "dot",
      "geometry": "default"
    },
    {
      "id": "D8.3",
      "horror": 1519.7738274536755,
      "dim": 8,
      "sub_level": 3,
      "timestamp": "2026-01-20T20:31:13.776506",
      "desc": "Dolor cr\u00f3nico / enfermedad inducida (iatrogenia sistema) agravado x1.63",
      "label": "D8.3",
      "position": [
        -356.4275929515217,
        19.675701563728097,
        -633.5729943863753
      ],
      "shape": "dot",
      "geometry": "default"
    },
    {
      "id": "D8.4",
      "horror": 1452.150175054925,
      "dim": 8,
      "sub_level": 4,
      "timestamp": "2026-01-20T20:31:13.776506",
      "desc": "Dolor cr\u00f3nico / enfermedad inducida (iatrogenia sistema) agravado x1.64",
      "label": "D8.4",
      "position": [
        -176.40731780401788,
        101.06668120234917,
        -722.9563133593069
      ],
      "shape": "dot",
      "geometry": "default"
    },
    {
      "id": "D8.5",
      "horror": 1440.52903326934,
      "dim": 8,
      "sub_level": 5,
      "timestamp": "2026-01-20T20:31:13.776506",
      "desc": "Dolor cr\u00f3nico / enfermedad inducida (iatrogenia sistema) agravado x1.44",
      "label": "D8.5",
      "position": [
        -216.86542562677,
        125.94751368456156,
        -766.8724301818
      ],
      "shape": "dot",
      "geometry": "default"
    },
    {
      "id": "D8.6",
      "horror": 1693.2540586508194,
      "dim": 8,
      "sub_level": 6,
      "timestamp": "2026-01-20T20:31:13.776506",
      "desc": "Dolor cr\u00f3nico / enfermedad inducida (iatrogenia sistema) agravado x1.83",
      "label": "D8.6",
      "position": [
        -185.59799489125766,
        -23.596925779081346,
        -723.7853985020124
      ],
      "shape": "dot",
      "geometry": "default"
    },
    {
      "id": "D8.7",
      "horror": 1556.0576161086578,
      "dim": 8,
      "sub_level": 7,
      "timestamp": "2026-01-20T20:31:13.776506",
      "desc": "Dolor cr\u00f3nico / enfermedad inducida (iatrogenia sistema) agravado x1.57",
      "label": "D8.7",
      "position": [
        -133.57025570549632,
        -57.75345576572276,
        -845.9518001320534
      ],
      "shape": "dot",
      "geometry": "default"
    },
    {
      "id": "D8.8",
      "horror": 1361.4317791622627,
      "dim": 8,
      "sub_level": 8,
      "timestamp": "2026-01-20T20:31:13.776506",
      "desc": "Dolor cr\u00f3nico / enfermedad inducida (iatrogenia sistema) agravado x1.40",
      "label": "D8.8",
      "position": [
        -233.26746801348946,
        -98.02327877357257,
        -569.2629625413417
      ],
      "shape": "dot",
      "geometry": "default"
    },
    {
      "id": "D9",
      "horror": 996.6076642859011,
      "dim": 9,
      "timestamp": "2026-01-20T20:31:13.776506",
      "desc": "Autodestrucci\u00f3n inevitable (sistema gana, t\u00fa pierdes)",
      "label": "D9: Autodestrucci\u00f3n inevitable (sistema gana, t\u00fa pierdes)",
      "position": [
        55.72522067386706,
        485.7156465685696,
        140.361892800477
      ],
      "shape": "sphere",
      "geometry": "default"
    },
    {
      "id": "D9.1",
      "horror": 1136.4625073710952,
      "dim": 9,
      "sub_level": 1,
      "timestamp": "2026-01-20T20:31:13.776506",
      "desc": "Autodestrucci\u00f3n inevitable (sistema gana, t\u00fa pierdes) agravado x1.41",
      "label": "D9.1",
      "position": [
        -92.77403551124493,
        592.4639676644678,
        171.7279121459024
      ],
      "shape": "dot",
      "geometry": "default"
    },
    {
      "id": "D9.2",
      "horror": 1380.2299226457715,
      "dim": 9,
      "sub_level": 2,
      "timestamp": "2026-01-20T20:31:13.776506",
      "desc": "Autodestrucci\u00f3n inevitable (sistema gana, t\u00fa pierdes) agravado x1.59",
      "label": "D9.2",
      "position": [
        32.902672800408226,
        373.3969127387049,
        255.676664953812
      ],
      "shape": "dot",
      "geometry": "default"
    },
    {
      "id": "D9.3",
      "horror": 1262.4710572091785,
      "dim": 9,
      "sub_level": 3,
      "timestamp": "2026-01-20T20:31:13.776506",
      "desc": "Autodestrucci\u00f3n inevitable (sistema gana, t\u00fa pierdes) agravado x1.61",
      "label": "D9.3",
      "position": [
        176.68969004293962,
        533.7695307979811,
        42.425365050656666
      ],
      "shape": "dot",
      "geometry": "default"
    },
    {
      "id": "D9.4",
      "horror": 1381.2041762926044,
      "dim": 9,
      "sub_level": 4,
      "timestamp": "2026-01-20T20:31:13.776506",
      "desc": "Autodestrucci\u00f3n inevitable (sistema gana, t\u00fa pierdes) agravado x1.74",
      "label": "D9.4",
      "position": [
        -32.70825884098866,
        350.2998884274658,
        266.03516175709126
      ],
      "shape": "dot",
      "geometry": "default"
    },
    {
      "id": "D9.5",
      "horror": 1368.1494704571005,
      "dim": 9,
      "sub_level": 5,
      "timestamp": "2026-01-20T20:31:13.776506",
      "desc": "Autodestrucci\u00f3n inevitable (sistema gana, t\u00fa pierdes) agravado x1.84",
      "label": "D9.5",
      "position": [
        178.09175459438381,
        432.28882106607523,
        99.36869999613207
      ],
      "shape": "dot",
      "geometry": "default"
    },
    {
      "id": "D9.6",
      "horror": 1317.3272409472343,
      "dim": 9,
      "sub_level": 6,
      "timestamp": "2026-01-20T20:31:13.776506",
      "desc": "Autodestrucci\u00f3n inevitable (sistema gana, t\u00fa pierdes) agravado x1.61",
      "label": "D9.6",
      "position": [
        -87.99012038247568,
        579.9353585773529,
        36.2451751798655
      ],
      "shape": "dot",
      "geometry": "default"
    },
    {
      "id": "D9.7",
      "horror": 1347.0275994548135,
      "dim": 9,
      "sub_level": 7,
      "timestamp": "2026-01-20T20:31:13.776506",
      "desc": "Autodestrucci\u00f3n inevitable (sistema gana, t\u00fa pierdes) agravado x1.39",
      "label": "D9.7",
      "position": [
        21.841826088829364,
        505.59862771789824,
        75.36225481118444
      ],
      "shape": "dot",
      "geometry": "default"
    },
    {
      "id": "D9.8",
      "horror": 1417.213301869936,
      "dim": 9,
      "sub_level": 8,
      "timestamp": "2026-01-20T20:31:13.776506",
      "desc": "Autodestrucci\u00f3n inevitable (sistema gana, t\u00fa pierdes) agravado x1.62",
      "label": "D9.8",
      "position": [
        -45.08982062718928,
        587.0540376340955,
        1.5530527351664887
      ],
      "shape": "dot",
      "geometry": "default"
    },
    {
      "id": "HYBRID_D1.2_D6",
      "horror": 2392.0722430469277,
      "dim": "HYBRID",
      "desc": "Traici\u00f3n destruye Vac\u00edo visceral",
      "label": "Traici\u00f3n destruye Vac\u00edo visceral",
      "position": [
        -335.63989237024634,
        -280.69578336333257,
        -242.9699864681133
      ],
      "geometry": "default"
    },
    {
      "id": "HYBRID_D1.7_D8.7",
      "horror": 2235.028328118557,
      "dim": "HYBRID",
      "desc": "Traici\u00f3n traiciona Dolor eterno",
      "label": "Traici\u00f3n traiciona Dolor eterno",
      "position": [
        -178.68086882442626,
        -29.610318305319517,
        -801.4337554824046
      ],
      "geometry": "default"
    },
    {
      "id": "HYBRID_D3_D8.1",
      "horror": 2030.9594724206186,
      "dim": "HYBRID",
      "desc": "Aislamiento asfixia Dolor cognitivo",
      "label": "Aislamiento asfixia Dolor cognitivo",
      "position": [
        117.38090908500504,
        5.15013573176094,
        -637.5630306890475
      ],
      "geometry": "default"
    },
    {
      "id": "HYBRID_D3.4_D7.5",
      "horror": 2636.534374014218,
      "dim": "HYBRID",
      "desc": "Aislamiento asfixia Humillaci\u00f3n irreparable",
      "label": "Aislamiento asfixia Humillaci\u00f3n irreparable",
      "position": [
        256.35650643489066,
        -304.33761703529603,
        -398.80667091907105
      ],
      "geometry": "default"
    },
    {
      "id": "HYBRID_D4.8_D7.8",
      "horror": 2679.744895013027,
      "dim": "HYBRID",
      "desc": "Muerte asfixia Humillaci\u00f3n existencial",
      "label": "Muerte asfixia Humillaci\u00f3n existencial",
      "position": [
        88.87730202477162,
        -538.447685956211,
        -417.6545812484089
      ],
      "geometry": "default"
    },
    {
      "id": "HYBRID_D5_D1.7",
      "horror": 2110.98817840137,
      "dim": "HYBRID",
      "desc": "Colapso traiciona Traici\u00f3n iatrog\u00e9nico",
      "label": "Colapso traiciona Traici\u00f3n iatrog\u00e9nico",
      "position": [
        -137.89330765093297,
        327.79444171511415,
        -190.43090157728642
      ],
      "geometry": "default"
    },
    {
      "id": "HYBRID_D5.2_D3.8",
      "horror": 2279.708596189543,
      "dim": "HYBRID",
      "desc": "Colapso traiciona Aislamiento c\u00f3smico",
      "label": "Colapso traiciona Aislamiento c\u00f3smico",
      "position": [
        388.5989879106164,
        358.3299124222846,
        -136.50638536477305
      ],
      "geometry": "default"
    },
    {
      "id": "HYBRID_D7.3_D2.6",
      "horror": 2317.9248424928733,
      "dim": "HYBRID",
      "desc": "Humillaci\u00f3n humilla Colapso iatrog\u00e9nico",
      "label": "Humillaci\u00f3n humilla Colapso iatrog\u00e9nico",
      "position": [
        95.00630653230519,
        -258.45768867374784,
        270.14746962703197
      ],
      "geometry": "default"
    },
    {
      "id": "HYBRID_D8.3_D7",
      "horror": 2116.0628016138153,
      "dim": "HYBRID",
      "desc": "Dolor desgarra Humillaci\u00f3n terminal",
      "label": "Dolor desgarra Humillaci\u00f3n terminal",
      "position": [
        -176.0123336138723,
        -325.8501636500306,
        -323.0473676144558
      ],
      "geometry": "default"
    },
    {
      "id": "HYBRID_D9.7_D3.3",
      "horror": 2450.2875237188928,
      "dim": "HYBRID",
      "desc": "Autodestrucci\u00f3n perpet\u00faa Aislamiento visceral",
      "label": "Autodestrucci\u00f3n perpet\u00faa Aislamiento visceral",
      "position": [
        315.99697043268384,
        284.88636268671394,
        -303.87730081804904
      ],
      "geometry": "default"
    }
  ],
  "links": [
    {
      "source": "CERO_ABSOLUTO",
      "target": "D1",
      "weight": 1.0
    },
    {
      "source": "CERO_ABSOLUTO",
      "target": "D2",
      "weight": 1.0
    },
    {
      "source": "CERO_ABSOLUTO",
      "target": "D3",
      "weight": 1.0
    },
    {
      "source": "CERO_ABSOLUTO",
      "target": "D4",
      "weight": 1.0
    },
    {
      "source": "CERO_ABSOLUTO",
      "target": "D5",
      "weight": 1.0
    },
    {
      "source": "CERO_ABSOLUTO",
      "target": "D6",
      "weight": 1.0
    },
    {
      "source": "CERO_ABSOLUTO",
      "target": "D7",
      "weight": 1.0
    },
    {
      "source": "CERO_ABSOLUTO",
      "target": "D8",
      "weight": 1.0
    },
    {
      "source": "CERO_ABSOLUTO",
      "target": "D9",
      "weight": 1.0
    },
    {
      "source": "D1",
      "target": "D1.1",
      "weight": 1.6358807911638604
    },
    {
      "source": "D1",
      "target": "D1.2",
      "weight": 1.7579283372155072
    },
    {
      "source": "D1",
      "target": "D1.3",
      "weight": 1.431358108168908
    },
    {
      "source": "D1",
      "target": "D1.4",
      "weight": 1.676418144050055
    },
    {
      "source": "D1",
      "target": "D1.5",
      "weight": 1.4263710384676824
    },
    {
      "source": "D1",
      "target": "D1.6",
      "weight": 1.3897298827297404
    },
    {
      "source": "D1",
      "target": "D1.7",
      "weight": 1.5336935853496267
    },
    {
      "source": "D1",
      "target": "D1.8",
      "weight": 1.602785669289033
    },
    {
      "source": "D1.1",
      "target": "D3.7",
      "weight": 0.849447758725973
    },
    {
      "source": "D1.2",
      "target": "D6",
      "weight": 1.9320650394670909
    },
    {
      "source": "D1.2",
      "target": "HYBRID_D1.2_D6",
      "weight": 2.0
    },
    {
      "source": "D1.4",
      "target": "D9.2",
      "weight": 0.9255311728635081
    },
    {
      "source": "D1.7",
      "target": "D8.7",
      "weight": 1.5916836146412756
    },
    {
      "source": "D1.7",
      "target": "HYBRID_D1.7_D8.7",
      "weight": 2.0
    },
    {
      "source": "D1.7",
      "target": "HYBRID_D5_D1.7",
      "weight": 2.0
    },
    {
      "source": "D1.8",
      "target": "D2.8",
      "weight": 1.1622548225640157
    },
    {
      "source": "D2",
      "target": "D2.1",
      "weight": 1.4921802863166924
    },
    {
      "source": "D2",
      "target": "D2.2",
      "weight": 1.762115348044901
    },
    {
      "source": "D2",
      "target": "D2.3",
      "weight": 1.6916547520215917
    },
    {
      "source": "D2",
      "target": "D2.4",
      "weight": 1.8447799289269788
    },
    {
      "source": "D2",
      "target": "D2.5",
      "weight": 1.7244202618377635
    },
    {
      "source": "D2",
      "target": "D2.6",
      "weight": 1.363361604608451
    },
    {
      "source": "D2",
      "target": "D2.7",
      "weight": 1.8008984786961006
    },
    {
      "source": "D2",
      "target": "D2.8",
      "weight": 1.6918635387604462
    },
    {
      "source": "D2",
      "target": "D5.1",
      "weight": 1.172330863823361
    },
    {
      "source": "D2.5",
      "target": "D7.3",
      "weight": 0.9502817135759198
    },
    {
      "source": "D2.6",
      "target": "D4.2",
      "weight": 0.836561381192002
    },
    {
      "source": "D2.6",
      "target": "HYBRID_D7.3_D2.6",
      "weight": 2.0
    },
    {
      "source": "D3",
      "target": "D3.1",
      "weight": 1.6780323193006357
    },
    {
      "source": "D3",
      "target": "D3.2",
      "weight": 1.7289026504751868
    },
    {
      "source": "D3",
      "target": "D3.3",
      "weight": 1.7056048798282835
    },
    {
      "source": "D3",
      "target": "D3.4",
      "weight": 1.551016669858976
    },
    {
      "source": "D3",
      "target": "D3.5",
      "weight": 1.4224240992835533
    },
    {
      "source": "D3",
      "target": "D3.6",
      "weight": 1.7977953091328156
    },
    {
      "source": "D3",
      "target": "D3.7",
      "weight": 1.5465621182684877
    },
    {
      "source": "D3",
      "target": "D3.8",
      "weight": 1.453291616155393
    },
    {
      "source": "D3",
      "target": "D8.1",
      "weight": 1.7956516564211475
    },
    {
      "source": "D3",
      "target": "HYBRID_D3_D8.1",
      "weight": 2.0
    },
    {
      "source": "D3.3",
      "target": "D6.6",
      "weight": 0.9539248879442916
    },
    {
      "source": "D3.3",
      "target": "HYBRID_D9.7_D3.3",
      "weight": 2.0
    },
    {
      "source": "D3.4",
      "target": "D7.5",
      "weight": 1.8846680718543922
    },
    {
      "source": "D3.4",
      "target": "HYBRID_D3.4_D7.5",
      "weight": 2.0
    },
    {
      "source": "D3.7",
      "target": "D2.2",
      "weight": 1.3910742585771154
    },
    {
      "source": "D3.8",
      "target": "D7.3",
      "weight": 1.3834096544074495
    },
    {
      "source": "D3.8",
      "target": "HYBRID_D5.2_D3.8",
      "weight": 2.0
    },
    {
      "source": "D4",
      "target": "D4.1",
      "weight": 1.7712278288970915
    },
    {
      "source": "D4",
      "target": "D4.2",
      "weight": 1.6129650177815142
    },
    {
      "source": "D4",
      "target": "D4.3",
      "weight": 1.7440633912590748
    },
    {
      "source": "D4",
      "target": "D4.4",
      "weight": 1.7982750336480562
    },
    {
      "source": "D4",
      "target": "D4.5",
      "weight": 1.384254648957085
    },
    {
      "source": "D4",
      "target": "D4.6",
      "weight": 1.394408978031231
    },
    {
      "source": "D4",
      "target": "D4.7",
      "weight": 1.8124886055465097
    },
    {
      "source": "D4",
      "target": "D4.8",
      "weight": 1.404913657411507
    },
    {
      "source": "D4.1",
      "target": "D1.8",
      "weight": 0.9538732085625032
    },
    {
      "source": "D4.3",
      "target": "D1.7",
      "weight": 0.845236869515049
    },
    {
      "source": "D4.5",
      "target": "D1.6",
      "weight": 1.3884867434649095
    },
    {
      "source": "D4.8",
      "target": "D7.8",
      "weight": 1.79300293061159
    },
    {
      "source": "D4.8",
      "target": "HYBRID_D4.8_D7.8",
      "weight": 2.0
    },
    {
      "source": "D5",
      "target": "D5.1",
      "weight": 1.810023306134167
    },
    {
      "source": "D5",
      "target": "D5.2",
      "weight": 1.5595621641731905
    },
    {
      "source": "D5",
      "target": "D5.3",
      "weight": 1.6939801068235305
    },
    {
      "source": "D5",
      "target": "D5.4",
      "weight": 1.6248583840486017
    },
    {
      "source": "D5",
      "target": "D5.5",
      "weight": 1.460820428335262
    },
    {
      "source": "D5",
      "target": "D5.6",
      "weight": 1.687956848335147
    },
    {
      "source": "D5",
      "target": "D5.7",
      "weight": 1.6623999621904646
    },
    {
      "source": "D5",
      "target": "D5.8",
      "weight": 1.5855574816699436
    },
    {
      "source": "D5",
      "target": "D1.7",
      "weight": 1.7929070165187149
    },
    {
      "source": "D5",
      "target": "HYBRID_D5_D1.7",
      "weight": 2.0
    },
    {
      "source": "D5.2",
      "target": "D3.8",
      "weight": 1.5928212094744172
    },
    {
      "source": "D5.2",
      "target": "HYBRID_D5.2_D3.8",
      "weight": 2.0
    },
    {
      "source": "D5.3",
      "target": "D7.8",
      "weight": 0.9811924833342767
    },
    {
      "source": "D5.6",
      "target": "D1.3",
      "weight": 0.8527815205831043
    },
    {
      "source": "D6",
      "target": "D6.1",
      "weight": 1.400767584773263
    },
    {
      "source": "D6",
      "target": "D6.2",
      "weight": 1.7030408313383893
    },
    {
      "source": "D6",
      "target": "D6.3",
      "weight": 1.422183721533728
    },
    {
      "source": "D6",
      "target": "D6.4",
      "weight": 1.7473473441586496
    },
    {
      "source": "D6",
      "target": "D6.5",
      "weight": 1.441029719731254
    },
    {
      "source": "D6",
      "target": "D6.6",
      "weight": 1.3699968775032447
    },
    {
      "source": "D6",
      "target": "D6.7",
      "weight": 1.5507611448239274
    },
    {
      "source": "D6",
      "target": "D6.8",
      "weight": 1.6589108399471377
    },
    {
      "source": "D6",
      "target": "HYBRID_D1.2_D6",
      "weight": 2.0
    },
    {
      "source": "D6.1",
      "target": "D8",
      "weight": 0.9052950112088172
    },
    {
      "source": "D6.8",
      "target": "D5.7",
      "weight": 0.9462141833414621
    },
    {
      "source": "D7",
      "target": "D7.1",
      "weight": 1.6702554455708531
    },
    {
      "source": "D7",
      "target": "D7.2",
      "weight": 1.479576695911704
    },
    {
      "source": "D7",
      "target": "D7.3",
      "weight": 1.3880581405400025
    },
    {
      "source": "D7",
      "target": "D7.4",
      "weight": 1.405923944091878
    },
    {
      "source": "D7",
      "target": "D7.5",
      "weight": 1.576532918638872
    },
    {
      "source": "D7",
      "target": "D7.6",
      "weight": 1.7904936659811237
    },
    {
      "source": "D7",
      "target": "D7.7",
      "weight": 1.3663153728299915
    },
    {
      "source": "D7",
      "target": "D7.8",
      "weight": 1.6600959975476883
    },
    {
      "source": "D7",
      "target": "HYBRID_D8.3_D7",
      "weight": 2.0
    },
    {
      "source": "D7.3",
      "target": "D2.6",
      "weight": 1.7096156582226105
    },
    {
      "source": "D7.3",
      "target": "HYBRID_D7.3_D2.6",
      "weight": 2.0
    },
    {
      "source": "D7.4",
      "target": "D3.8",
      "weight": 0.9311569408189693
    },
    {
      "source": "D7.5",
      "target": "HYBRID_D3.4_D7.5",
      "weight": 2.0
    },
    {
      "source": "D7.5",
      "target": "D4.3",
      "weight": 1.169442022775271
    },
    {
      "source": "D7.8",
      "target": "HYBRID_D4.8_D7.8",
      "weight": 2.0
    },
    {
      "source": "D8",
      "target": "D8.1",
      "weight": 1.5607770966603174
    },
    {
      "source": "D8",
      "target": "D8.2",
      "weight": 1.3624696206511386
    },
    {
      "source": "D8",
      "target": "D8.3",
      "weight": 1.625121354216732
    },
    {
      "source": "D8",
      "target": "D8.4",
      "weight": 1.636031383593308
    },
    {
      "source": "D8",
      "target": "D8.5",
      "weight": 1.4355430588361398
    },
    {
      "source": "D8",
      "target": "D8.6",
      "weight": 1.8295883423995132
    },
    {
      "source": "D8",
      "target": "D8.7",
      "weight": 1.5684313519770856
    },
    {
      "source": "D8",
      "target": "D8.8",
      "weight": 1.3961015654936393
    },
    {
      "source": "D8.1",
      "target": "HYBRID_D3_D8.1",
      "weight": 2.0
    },
    {
      "source": "D8.2",
      "target": "D5.1",
      "weight": 0.9395682412721357
    },
    {
      "source": "D8.3",
      "target": "D7",
      "weight": 1.8549005659641025
    },
    {
      "source": "D8.3",
      "target": "HYBRID_D8.3_D7",
      "weight": 2.0
    },
    {
      "source": "D8.4",
      "target": "D9.2",
      "weight": 1.0409835561321292
    },
    {
      "source": "D8.5",
      "target": "D2.4",
      "weight": 1.2383061709666383
    },
    {
      "source": "D8.6",
      "target": "D4.4",
      "weight": 0.9259314555769034
    },
    {
      "source": "D8.7",
      "target": "HYBRID_D1.7_D8.7",
      "weight": 2.0
    },
    {
      "source": "D8.7",
      "target": "D5.6",
      "weight": 1.2952968098779998
    },
    {
      "source": "D8.8",
      "target": "D3.8",
      "weight": 1.3260584337866206
    },
    {
      "source": "D9",
      "target": "D9.1",
      "weight": 1.405000924403998
    },
    {
      "source": "D9",
      "target": "D9.2",
      "weight": 1.5857239825789606
    },
    {
      "source": "D9",
      "target": "D9.3",
      "weight": 1.6141111243183088
    },
    {
      "source": "D9",
      "target": "D9.4",
      "weight": 1.73684541464134
    },
    {
      "source": "D9",
      "target": "D9.5",
      "weight": 1.836510774850578
    },
    {
      "source": "D9",
      "target": "D9.6",
      "weight": 1.6068697026314127
    },
    {
      "source": "D9",
      "target": "D9.7",
      "weight": 1.3871150521265292
    },
    {
      "source": "D9",
      "target": "D9.8",
      "weight": 1.6204189727669158
    },
    {
      "source": "D9",
      "target": "D4.6",
      "weight": 1.23919724304968
    },
    {
      "source": "D9.5",
      "target": "D6",
      "weight": 0.9954117115959893
    },
    {
      "source": "D9.7",
      "target": "D3.3",
      "weight": 1.8865638241983953
    },
    {
      "source": "D9.7",
      "target": "HYBRID_D9.7_D3.3",
      "weight": 2.0
    },
    {
      "source": "D9.8",
      "target": "D4.1",
      "weight": 1.221572904785949
    }
  ],
  "clusters": [
    {
      "dim": 0,
      "horror_total": 1317.6249986397097,
      "node_count": 1,
      "mini_singularity": {
        "size": 5,
        "mass": 8.784166657598064
      }
    },
    {
      "dim": 1,
      "horror_total": 13741.467895392418,
      "node_count": 9,
      "mini_singularity": {
        "size": 5,
        "mass": 91.60978596928278
      }
    },
    {
      "dim": 2,
      "horror_total": 15923.279675271016,
      "node_count": 9,
      "mini_singularity": {
        "size": 5,
        "mass": 106.15519783514011
      }
    },
    {
      "dim": 3,
      "horror_total": 13900.589526134043,
      "node_count": 9,
      "mini_singularity": {
        "size": 5,
        "mass": 92.67059684089362
      }
    },
    {
      "dim": 4,
      "horror_total": 16421.310148821005,
      "node_count": 9,
      "mini_singularity": {
        "size": 5,
        "mass": 109.47540099214004
      }
    },
    {
      "dim": 5,
      "horror_total": 13927.277092167331,
      "node_count": 9,
      "mini_singularity": {
        "size": 5,
        "mass": 92.84851394778221
      }
    },
    {
      "dim": 6,
      "horror_total": 11367.42574102376,
      "node_count": 9,
      "mini_singularity": {
        "size": 5,
        "mass": 75.78283827349173
      }
    },
    {
      "dim": 7,
      "horror_total": 13753.213960035755,
      "node_count": 9,
      "mini_singularity": {
        "size": 5,
        "mass": 91.68809306690504
      }
    },
    {
      "dim": 8,
      "horror_total": 13022.139795383835,
      "node_count": 9,
      "mini_singularity": {
        "size": 5,
        "mass": 86.8142653025589
      }
    },
    {
      "dim": 9,
      "horror_total": 11606.692940533634,
      "node_count": 9,
      "mini_singularity": {
        "size": 5,
        "mass": 77.37795293689089
      }
    },
    {
      "dim": "HYBRID",
      "horror_total": 23249.311255029843,
      "node_count": 10,
      "mini_singularity": {
        "size": 5,
        "mass": 154.99540836686563
      }
    }
  ],
  "modo": "MODO BESTIA",
  "modo_info": {
    "threshold": 90000,
    "desc": "\ud83d\udc79 Bestia total \u2013 risa loca, \u03a6 eliminado",
    "color": "#ff0000",
    "emoji": "\ud83d\udc79",
    "physics": {
      "gravity": -50000,
      "spring_length": 30,
      "spring_strength": 0.15
    },
    "node_shape": "star",
    "geometry": "chaotic_burst"
  },
  "horror_total": 148230.33302843242
}